Workbook
Name \a: #REF!
Name __________________num031: IF(ISERROR(FIND(")+",Text03,230)),LEN(Text03),FIND(")+",Text03,230))
Name __________________num032: IF(ISERROR(FIND(")+",text03_1,230)),LEN(text03_1),FIND(")+",text03_1,230))
Name __________________num033: IF(ISERROR(FIND(")+",text03_2,230)),LEN(text03_2),FIND(")+",text03_2,230))
Name __________________num1: IF(ISERROR(FIND(")+",_xleta.TEXT,230)),LEN(_xleta.TEXT),FIND(")+",_xleta.TEXT,230))
Name __________________num2: IF(ISERROR(FIND(")+",text_1,230)),LEN(text_1),FIND(")+",text_1,230))
Name __________________num3: IF(ISERROR(FIND(")+",text_2,230)),LEN(text_2),FIND(")+",text_2,230))
Name _________________num031: IF(ISERROR(FIND(")+",Text03,230)),LEN(Text03),FIND(")+",Text03,230))
Name _________________num032: IF(ISERROR(FIND(")+",text03_1,230)),LEN(text03_1),FIND(")+",text03_1,230))
Name _________________num033: IF(ISERROR(FIND(")+",text03_2,230)),LEN(text03_2),FIND(")+",text03_2,230))
Name _________________num1: IF(ISERROR(FIND(")+",_xleta.TEXT,230)),LEN(_xleta.TEXT),FIND(")+",_xleta.TEXT,230))
Name _________________num2: IF(ISERROR(FIND(")+",text_1,230)),LEN(text_1),FIND(")+",text_1,230))
Name _________________num3: IF(ISERROR(FIND(")+",text_2,230)),LEN(text_2),FIND(")+",text_2,230))
Name ________________num031: IF(ISERROR(FIND(")+",Text03,230)),LEN(Text03),FIND(")+",Text03,230))
Name ________________num032: IF(ISERROR(FIND(")+",text03_1,230)),LEN(text03_1),FIND(")+",text03_1,230))
Name ________________NUM0321: IF(ISERROR(FIND(")+",text03_1,230)),LEN(text03_1),FIND(")+",text03_1,230))
Name ________________num033: IF(ISERROR(FIND(")+",text03_2,230)),LEN(text03_2),FIND(")+",text03_2,230))
Name ________________num1: IF(ISERROR(FIND(")+",_xleta.TEXT,230)),LEN(_xleta.TEXT),FIND(")+",_xleta.TEXT,230))
Name ________________num2: IF(ISERROR(FIND(")+",text_1,230)),LEN(text_1),FIND(")+",text_1,230))
Name ________________num3: IF(ISERROR(FIND(")+",text_2,230)),LEN(text_2),FIND(")+",text_2,230))
Name _______________num031: IF(ISERROR(FIND(")+",Text03,230)),LEN(Text03),FIND(")+",Text03,230))
Name _______________num032: IF(ISERROR(FIND(")+",text03_1,230)),LEN(text03_1),FIND(")+",text03_1,230))
Name _______________num033: IF(ISERROR(FIND(")+",text03_2,230)),LEN(text03_2),FIND(")+",text03_2,230))
Name _______________num1: IF(ISERROR(FIND(")+",_xleta.TEXT,230)),LEN(_xleta.TEXT),FIND(")+",_xleta.TEXT,230))
Name _______________num2: IF(ISERROR(FIND(")+",text_1,230)),LEN(text_1),FIND(")+",text_1,230))
Name _______________num3: IF(ISERROR(FIND(")+",text_2,230)),LEN(text_2),FIND(")+",text_2,230))
Name ______________num031: IF(ISERROR(FIND(")+",Text03,230)),LEN(Text03),FIND(")+",Text03,230))
Name ______________num032: IF(ISERROR(FIND(")+",text03_1,230)),LEN(text03_1),FIND(")+",text03_1,230))
Name ______________num033: IF(ISERROR(FIND(")+",text03_2,230)),LEN(text03_2),FIND(")+",text03_2,230))
Name ______________num1: IF(ISERROR(FIND(")+",_xleta.TEXT,230)),LEN(_xleta.TEXT),FIND(")+",_xleta.TEXT,230))
Name ______________num2: IF(ISERROR(FIND(")+",text_1,230)),LEN(text_1),FIND(")+",text_1,230))
Name ______________num3: IF(ISERROR(FIND(")+",text_2,230)),LEN(text_2),FIND(")+",text_2,230))
Name _____________num031: IF(ISERROR(FIND(")+",Text03,230)),LEN(Text03),FIND(")+",Text03,230))
Name _____________num032: IF(ISERROR(FIND(")+",text03_1,230)),LEN(text03_1),FIND(")+",text03_1,230))
Name _____________NUM0321: IF(ISERROR(FIND(")+",text03_1,230)),LEN(text03_1),FIND(")+",text03_1,230))
Name _____________num033: IF(ISERROR(FIND(")+",text03_2,230)),LEN(text03_2),FIND(")+",text03_2,230))
Name _____________num1: IF(ISERROR(FIND(")+",_xleta.TEXT,230)),LEN(_xleta.TEXT),FIND(")+",_xleta.TEXT,230))
Name _____________num2: IF(ISERROR(FIND(")+",text_1,230)),LEN(text_1),FIND(")+",text_1,230))
Name _____________num3: IF(ISERROR(FIND(")+",text_2,230)),LEN(text_2),FIND(")+",text_2,230))
Name ____________num031: IF(ISERROR(FIND(")+",Text03,230)),LEN(Text03),FIND(")+",Text03,230))
Name ____________num032: IF(ISERROR(FIND(")+",text03_1,230)),LEN(text03_1),FIND(")+",text03_1,230))
Name ____________NUM0321: IF(ISERROR(FIND(")+",text03_1,230)),LEN(text03_1),FIND(")+",text03_1,230))
Name ____________num033: IF(ISERROR(FIND(")+",text03_2,230)),LEN(text03_2),FIND(")+",text03_2,230))
Name ____________num1: IF(ISERROR(FIND(")+",_xleta.TEXT,230)),LEN(_xleta.TEXT),FIND(")+",_xleta.TEXT,230))
Name ____________num2: IF(ISERROR(FIND(")+",text_1,230)),LEN(text_1),FIND(")+",text_1,230))
Name ____________num3: IF(ISERROR(FIND(")+",text_2,230)),LEN(text_2),FIND(")+",text_2,230))
Name ___________num031: IF(ISERROR(FIND(")+",Text03,230)),LEN(Text03),FIND(")+",Text03,230))
Name ___________num032: IF(ISERROR(FIND(")+",[1]!text03_1,230)),LEN([1]!text03_1),FIND(")+",[1]!text03_1,230))
Name ___________NUM0321: IF(ISERROR(FIND(")+",[1]!text03_1,230)),LEN([1]!text03_1),FIND(")+",[1]!text03_1,230))
Name ___________num033: IF(ISERROR(FIND(")+",[1]!text03_2,230)),LEN([1]!text03_2),FIND(")+",[1]!text03_2,230))
Name ___________num1: IF(ISERROR(FIND(")+",_xleta.TEXT,230)),LEN(_xleta.TEXT),FIND(")+",_xleta.TEXT,230))
Name ___________num2: IF(ISERROR(FIND(")+",[1]!text_1,230)),LEN([1]!text_1),FIND(")+",[1]!text_1,230))
Name ___________num3: IF(ISERROR(FIND(")+",[1]!text_2,230)),LEN([1]!text_2),FIND(")+",[1]!text_2,230))
Name __________num031: IF(ISERROR(FIND(")+",Text03,230)),LEN(Text03),FIND(")+",Text03,230))
Name __________num032: IF(ISERROR(FIND(")+",[1]!text03_1,230)),LEN([1]!text03_1),FIND(")+",[1]!text03_1,230))
Name __________NUM0321: IF(ISERROR(FIND(")+",[1]!text03_1,230)),LEN([1]!text03_1),FIND(")+",[1]!text03_1,230))
Name __________num033: IF(ISERROR(FIND(")+",[1]!text03_2,230)),LEN([1]!text03_2),FIND(")+",[1]!text03_2,230))
Name __________num1: IF(ISERROR(FIND(")+",_xleta.TEXT,230)),LEN(_xleta.TEXT),FIND(")+",_xleta.TEXT,230))
Name __________num2: IF(ISERROR(FIND(")+",[1]!text_1,230)),LEN([1]!text_1),FIND(")+",[1]!text_1,230))
Name __________num3: IF(ISERROR(FIND(")+",[1]!text_2,230)),LEN([1]!text_2),FIND(")+",[1]!text_2,230))

Sheet Cover
A2: CHN, Shanghai Campus Building 1 RF Project
A3: Build General Contractor Works
A4: Issue Date:
A6: Name of Tenderer:__________________________________
A8: 1 | B8: The direct subcontract packages (contractual parties: Microsoft and vendor): | D8: IT/ AV/ Security (GC to complete conduit work); System furniture & loose furniture.
A9: 2 | B9: Items are Included in Main Contract scope of works | D9: Listed as below:
D10: Construction
D11: Electrical/ Plumbing & drainage works
D12: Air-conditioning
D13: Fire Services
A14: 3 | B14: Material Request | D14: SOR should based on "FF&E and Internal Finishes Schedule"
A15: 4 | B15: Material Sample Board | D15: Bidders are to submitt material board for review and approval
A16: 5 | B16: The following descriptions is not to be changed, otherwise, your proposal will not be considered. All the items should be quoted. "0.00" price should be noted with "included" or "not provided", otherwise it will be interpreted as Included, no additional cost will be approved in future. Any new item should be put under the "other" category:
A17: 6 | B17: All item listed is for reference ONLY. Bidder(s) are responsible to validate the quantities in the BOQ and RFP and provide lump sum quotation with comprehensive reflection of the site conditions and the whole work scope. The contract will be a lump sum contract.

Sheet Summary
B1: Cost Summary
B3: Construction Area (Sqft) | C3: 38351.813
B4: Construction Area (Sqm) | C4: =C3*0.09290304 -> 3563
C8: PER Budget | D8: QS Estimation | E8: Vendor - A | F8: Vendor - B | G8: Vendor - C | H8: Vendor - D | I8: Vendor - E | J8: Historical
B9: Total Cost (USD) | C9: ='PER Budget'!B21 -> 10087575 | D9: ='QS Estimation'!B21 -> 10614203 | E9: ='Vendor Quotation'!C41 -> 10922446 | F9: ='Vendor Quotation'!D41 -> 11193181 | G9: ='Vendor Quotation'!E41 -> 10177153 | H9: ='Vendor Quotation'!F41 -> 11261479 | I9: ='Vendor Quotation'!G41 -> 11627647
B10: Unit Cost (USD/Sqm) | C10: =IFERROR(C9/$C$4,0) -> 2831.2027 | D10: =IFERROR(D9/$C$4,0) -> 2979.0072 | E10: =IFERROR(E9/$C$4,0) -> 3065.5194 | F10: =IFERROR(F9/$C$4,0) -> 3141.5046 | G10: =IFERROR(G9/$C$4,0) -> 2856.3439 | H10: =IFERROR(H9/$C$4,0) -> 3160.6733 | I10: =IFERROR(I9/$C$4,0) -> 3263.4429 | J10: ='[39]Historical Unit Rates'!B22 -> 2500
D11: =E13 -> 0 | E11: =E9/C9 -> 1.0827623 | F11: =F9/D9 -> 1.0545475 | G11: =G9/E9 -> 0.93176506 | H11: =H9/F9 -> 1.0061018 | I11: =I9/G9 -> 1.1425245

Sheet OUTPUT
A1: VISUALS
A2: Page1 | C2: Page2 | E2: Page3
A3: Executive Recommendation Card Cost Variance (Vendor Total Price vs. PER-Budget) | C3: Executive Decision Dashboard Cost Variance (Vendor Category Cost vs. QS Estimate ) | E3: Executive Decision Dashboard Cost Variance (Vendor Unit Price vs. Historical Unit Price )
A4: Vendor | B4: Approval Within PER(±10%) | C4: #VALUE! | D4: Variance ± 5% - Reasonable | E4: #VALUE! | F4: Variance ± 5% - Reasonable
B5: Approval with condition（±10%＜Variance≤±20%） Recommended Value/Potential Savings | D5: ±5%＜Variance≤±15% – Review required | F5: ±5%＜Variance≤±15% – Review required
B6: Reject(Variance＞±20%) | D6: Variance＞±15% – Significant cost concern | F6: Variance＞±15% – Significant cost concern

Sheet Introduction
A1: Bill of Quantity Introduction
A3: The BOQ is applied for CHN, Shanghai Campus Building 1 RF Project.
A5: 1 | B5: All Chinese and English descriptions are mainly in Chinese.
B6: 所有的中英文描述均以中文为主。
A8: 2 | B8: The descriptions given herein are not intended as complete descriptions of the items, but merely as indication of their extent. All details of the various items are as shown on the Drawings and described in the Specification.
B9: 附表中对各项目之说明并非作为各项目之完整说明，而概括地表示其范围。各项目之所有细则须按照工料规范及招标图纸所述的执行。
A11: 3 | B11: The Contractor's rates for the items contained in this Schedule of Rates shall be deemed to include cost of all incidentals of labor, material, plant (working or idle), supervision, general attendance, profit and all other things and matters etc. This rates shall be used for the purpose of assessing variations.
B12: 附表中各项目单价应包括人工、物料及损耗、机械、监督管理、现场、利润及一切按照合同及技术规范要求按时及令发包方满意的完成本工程不可或缺的一切有关的附件及费用等。填报的单价将被作为日后变更评估的依据。
A14: 4 | B14: All item listed is for reference ONLY. Bidder(s) are responsible to validate the quantities in the BOQ and RFP and provide lump sum quotation with comprehensive reflection of the site conditions and the whole work scope.
B15: BOQ中所有列项及参考数量仅供参考。投标单位需自行核实BOQ的数量和RFP，并提供综合反映现场条件和整个工作范围的总价报价。
A17: 5 | B17: The prices inserted by the Contractor are "lump sum" prices and will not be adjusted for any errors in the Contractor's measurement and pricing.
B18: 投标单位的投标总价为包干价，不会因投标单位的任何量度或报价计算错误而调整。
A20: 6 | B20: The Contractor shall be fully responsible for the accuracy of the quantities set out in the Schedule of Quantities and Rates on which his Tender has been based. The Contract Sum and rates will not be adjusted, except for the mechanism set out in the tender documents for the frame contracts.
B21: 对于单价表内之数量及单价，其准确与否的风险归承包单位；除招标文件中为框架合同约定的调价机制外，本合同总价及单价维持不变。
A23: 7 | B23: The Employer shall not be responsible for any omissions and errors in the description of items. The onus shall be on the Contractor to check the Tender Documents in details for any omissions and errors. Should such omissions and errors be discovered at any time, they shall be deemed to have been included in the prices of the relevant items.
B24: 发包方不会对本附表中的任何项目的缺失或项目描述的错误负责。投标单位须自行检查及复核，任何时候发现有上述缺失或错误，有关费用将被视为已包括于其他相关项目费用中。
A26: 8 | B26: Whenever the word "Allow" occurs in this Schedule of Rates, the cost of the items shall be at the risk of the Contractor and no adjustment will be made at the settlement of accounts. In the absence of any price against such items, the cost shall be deemed to be included in the rates of the other items.
B27: 附表中以“项”计的项目之价款为包干价，其准确与否的风险归承包单位，不论此等项目实际发生的费用与投标单位之估计有多大出入，亦不论有无设计变更，此等费用均不作调整。除非在不需要时，整项扣除。任何项目若没有填上价款的，其所需费用视作已包括在其他项目的价款或工程单价内。
A29: 9 | B29: The price of "Allow for other works not listed above" are deemed to include for all those works which are not listed in the Schedule of Rates but are required by the Contract according to the Drawings and Specification. The onus shall be on the Contractor to check for such works and price them in this item. If no price is inserted here, the costs are deemed to have been spread over the other items proportionately.
B30: “未列但图纸和/或规范和/或现场所需要之工作”为单价表内未列明但按招标图纸及技术规范要求所需之项目。投标单位需根据招标图纸及技术规范要求自行检查及填报此等项目。如投标单位未对此项目报价，则有关费用视作已包括在其他项目的价款或工程单价内。
A32: 10 | B32: The unit rates are to include for all the necessary testing and commissioning, cleaning includes all the materials, instruments, tools, labor in connection therewith.
B33: 此外,单价亦应包括各必须安装及测试、调核、试运行、清洁的材料、工具及工资(包括节假日，夜班及赶工费用)等费用。

Sheet Rules of measurement
A1: Measurement/pricing rules 计量/计价规则
A3: 1.0 General 总则
B5: 1.1 basic rules 基本规则
C7: 1.1.1 Purpose 目的
D8: "The purpose of this "Rules for Calculation of Quantities" is to provide a uniform unit of calculation and a standardized method of measurement for the calculation of quantities in the "Table of Unit Prices of Works", so that the offeror can calculate the quantities of the works and prepare accurate and feasible quotations on the basis of the uniformity. All quantities must be calculated in accordance with these rules, regardless of whether the quantities are provided by the Owner as "tentative quantities" or the quantities are calculated by the Offeror. The "Unit Price Statement" describes and defines the nature and content of all billable items in the quantity calculation rules. Each item in the unit price list must be bid in accordance with the requirements and bases of the "Unit Price Statement" and the "Rules for Calculation of Quantities"." 本“工程量计算规则”的目的是为计算“工程单价表”内的数量而提供统一的计算单位和标准的工程计量方法，以便报价人能在统一的基础下自算工程量及编制准确可行的报价。不论是由业主方提供之“暂定数量”项目的工程量，或由报价人自算的工程量，所有工程量必须按照本计算规则来计算。 “单价说明”是针对工程量计算规则中所有计费项目的性质与内容给予描述与定义。工程单价表中各项目必须根据“单价说明”及“工程量计算规则”的要求与依据来投价。
C10: 1.1.2 unit of measure 计量单位
D11: The following units of measure shall be used consistently, unless otherwise indicated later: 除后面另有说明外，须一致采用以下计量单位：
D12: (i) Items measured in volume - cubic meters (m3) 以体积为单位之项目－立方米（m3）
D13: (ii) Items in terms of area - square meters (sm) 以面积为单位之项目－平方米（sm）
D14: (iii) Items in length - meters (lm) 以长度为单位之项目－米（lm）
D15: (v) Item in pieces - quantity (nos.) 以件为单位之项目－数量（nos.）
D16: (vi) item of work measured in aggregate - item (sum) 综合计量某项工作－项（sum）
C18: 1.1.3 Unit accuracy of inventory preparation 编制清单的单位精度
D19: (1) In case of change or addition or deletion of items, increase or deletion of item quantities shall be calculated to the extent of 0.01 meter, 0.01 square meter, and 0.01 cubic meter. 在项目变更或增减时，项目工程量之增减须计算至0.01米、0.01平米、0.01立米。
D20: (2) Dimensions not stated in units in the list description are in millimeters. 在清单说明中未注明单位的尺寸均为毫米。
C22: 1.1.4 Net value 净值
D23: (1) Unless otherwise stated, all items are calculated on a net basis after installation in place, and any wear and tear needs to be taken into account in the composite unit price 除另有说明外，所有项目均以安装就位后的净值计算，任何损耗需要考虑在综合单价中
C25: 1.1.5 Costs included in the unit price 项目已包括的费用
D26: Unless otherwise indicated, the unit price or price for each item shall have included, but not be limited to, the following:
D27: (1) Labor and all related costs.
D28: (2) Materials, goods, and all related costs (e.g., transportation, delivery, unloading, storage, return of packing materials, handling, hoisting, and lowering).
D29: (3) In-situ assembly and installation of materials and goods.
D30: (4) Use of construction machinery.
D31: (5) All cutting and wastage.
D32: (6) Direct costs, risks and charges.
D33: (7) All costs required by the government and related agencies/departments.
D34: (8) Detailed drawings required for the construction and installation of the work.
D35: (9) Cost of consumable materials and appliances used.
D36: (10) Difference in cost between large-scale construction and small-scale construction.
D37: (11) The cost of liaison and coordination with other contractors, owners, architects, governmental agencies, etc. necessary for the construction.
... D55: （14）平面或立面呈弧型的额外工作费用
C57: 1.1.6
D58: Unless otherwise stated, the unit prices or rates in the schedule of unit prices are applicable to design and construction under all circumstances (i.e., including changes in depth, construction program, site conditions, varying soil quality, underground obstructions, etc.). Therefore, regardless of the circumstances under which the work is designed and constructed, the unit prices or rates in the schedule of unit prices will be the basis for pricing and will not be subject to additional adjustments. 除另有说明外，工程单价表内的单价或价款适用于所有情形下设计并施工（即包括深度变化、施工方案、现场情况、不同土质、地下障碍物等）。所以，不论任何情况下设计并施工，工程单价表内的单价或价款将成为计价的根据，并不会另外作出调整。
B60: 1.2 specialized term 专用术语
C61: 1.2.1 item“项”
D62: When the word "item" appears in the unit of quantity in the description of the item in the unit price list, the cost of the item is at the risk of the contractor and will not be adjusted at the final account, and if such an item is not quoted, the cost is deemed to have been included in other unit prices/price in the unit price list. If the item has never occurred, the amount of the item reported in the unit price list will be deducted from the final account. 当工程单价表项目说明的数量单位中出现“项”字样，则该项目的造价由承包单位承担风险，决算时不作调整，若此类项目没有报价，造价即视为已包括在工程单价表之其它单价/价款中。如该项目从来没有发生过，则决算时将把填报在单价表内的项目金额全部扣除。
C64: 1.2.2 Adjustments to the "provisional price" of materials 材料“暂定价款”的调整
D65: If the item description of the unit price list of the project appears in the "temporary price of materials", the "temporary price of materials" is only the price of materials delivered to the construction site for the project, the unit price of the project reported by the Contractor in addition to the "temporary price of materials" itself should be included. The unit price quoted by the Contractor for the project shall include, in addition to the price of the "tentative price of materials" itself, the costs of wear and tear, handling, installation, fees, and all other similar materials and operations such as cement, mortar, and other auxiliary materials required. 若工程单价表之项目说明中出现“材料暂定价款”，此“材料暂定价款”只为该项目材料交付到施工现场之价格，承包单位所投报该项目之单价除应包括“材料暂定价款”本身的价额外，还需包括损耗、装卸、安装、规费及所需要的辅助材料如水泥、砂浆等所有其它类似材料和作业的费用。
D67: The contract unit price will be adjusted by the net difference between the specified "provisional price of materials" and the "actual price of supply" and the actual cost will be calculated on the basis of the net value of the quantity of work involved in the construction of the project. 该合同单价将按指定的“材料暂定价款”及“实际供应价”之净差调整，并依据建造该项目工程量之净值来计算实际造价。
C69: 1.2.3 "Provisional number"“暂定数量”
D70: Unless specifically provided for in the Rules of Measurement, the quantities do not include any overlaps. For any material requiring varying degrees of overlap, such as reinforcing mesh flexible bedding or similar materials, the unit price quoted shall include the quantity of such overlap and splices. 除非工程计量规则中有特别规定，工程量中是不包括任何重迭量的。任何须有不同程度重迭搭接要求的材料，如钢筋网柔性垫料或类似材料，投报的单价中须已含此等重迭、搭接的数量。
A72: 2.0 Partition wall and steel frame wall works 隔墙及钢架墙工程
B73: 2.1 general provision 一般规定
D74: 2.1.1 Masonry walls shall be calculated in square meters, without distinction as to the type of blocks used, mortar grade and other requirements.
D75: 2.1.2 Walls of different types and thicknesses shall be calculated separately.
D76: 2.1.1 砌体墙应以平方米计算，不区分其采用的砌块类型，砂浆级别等要求。
D77: 2.1.2 不同类型和不同厚度的墙体须分别计算。
B79: 2.2 Bricks wall 一般砌体
C80: 2.2.1
D81: The area of the wall shall be deducted from the door and window openings and the holes over 0.3 square meters, and the area occupied by the head of the slab of the floor-roof panel of the ring beam over the beam, the structural columns, the gable beams, the horizontal wall parapet beams which are not load-bearing, the awning beams, the pressurized roof, the head of the beam, the beam pads, and the floor-roof panel shall not be deducted. Tiger tiles, finial lines, waistlines, etc., protruding from the wall are also not counted, but are considered to be included in the item. 墙身面积中应扣除门窗洞口和0.3平方米以上的洞孔，不扣除圈梁过梁、构造柱、檐口梁、不承重的卧墙花栏梁、雨篷梁、压顶、梁头、梁垫、楼屋面板的板头所占的面积。突出墙面的虎头砖、压顶线、腰线等也不计算，但视为已包含在该项目内。
C83: 2.2.2
D84: Walls that are circular in plan are measured in area by their average length and are itemized separately. 平面呈圆弧状的墙体以其平均长度来计量面积并单独立项。
C86: 2.2.3
D87: Structural columns & ring beams: need to meet the national norms for setting up 构造柱& 圈梁：需要满足国家规范进行设置
B89: 2.3 Unit prices for all masonry work shall be included 所有砌体工程之单价须包括：
C91: 2.3.1
D92: Each item of brick masonry, block wall and finish shall have included all cutting of bricks, trimming of clear surfaces, laying out of brick waist lines and recessed markers, leveling of arches and installation of leveling forms, tucking of bricks under blocks and beams, placing of wood bricks, adjusting of erected wood window and door frames, adjusting of mortar for holes in the flue, sealing of cornices, checking of hanging wires, laying of window and door casings, cutting of bricks at the head of corners, cutting of grooves, outlining of raised and recessed joints, leaving of holes and tongue-and-groove joints, and repairing and any other incidental items of a similar nature. 每项砖砌体、砌块墙体和饰面内均应已包括所有砍砖、修整净面、砌出砖腰线和凹进标线、平拱及安装平拱模板、按块和梁板下塞砖、安放木砖、调整立好后的木门窗框、烟道内孔调抹砂浆、封檐、吊线检查、砌门窗套、墙角按头砍砖、开槽口、勾凸凹缝、留孔洞和榫眼、以及修复和任何其他类似性质的零星项目。
C94: 2.3.2
D95: The entire process of preparing materials, dripping bricks, mixing mortar, laying mortar, brick masonry, hanging lines, keeping mortar joints full and straight, and sweeping walls. 准备材料、淋砖、拌合砂浆、铺砂浆、砖砌石、挂线、灰缝保持饱满、平直、清扫墙面等全部操作过程。
C97: 2.3.3
D98: Tie reinforcement at masonry wall corners at intersections with columns/slabs, etc., anchors, etc. The wall project also includes the necessary wire mesh, reinforcement, slots and holes. 砌体墙转角处与柱/板等交接处的拉结钢筋，锚固件等。墙体项目还包括所必需的钢丝网、加固件及开槽、孔等内容。
C100: 2.3.4
D101: The unit price of all hollow block walls shall include the use of solid blocks or cement mortar for door/window side closets, wire mesh reinforcement, and wall panel intersections. Ties, anchors, etc. between hollow walls are also considered to be included. 所有空心砖墙之单价须包括在门/窗侧壁橱，在钢丝网加固处，及墙板交接处使用实心砌块或用水泥砂浆封填整齐。空心墙体间的拉结件、锚固件等也认为已包括在内了。
B103: 2.4 Gypsum partition 石膏板隔墙
C105: 2.4.1
D106: The skeleton and gypsum board faces (or other panel materials) of all gypsum boards and other lightweight partitions will not be measured separately, but gypsum boards and other lightweight partitions of different thicknesses, rock wool capacities and assembly methods will be counted separately on a square meter basis. 所有石膏板及其他轻质隔墙的骨架与石膏板面(或其他面板材料)不会分开计量，而是按不同厚度、岩棉容重及组装方法分别以平方米计算。
C108: 2.4.2
D109: Gypsum boards and other lightweight partition walls of different types and thicknesses shall be calculated separately. 不同类型和不同厚度的石膏板等轻质隔墙须分别计算。
C111: 2.4.3
D112: The calculated area of the skeleton and panel faces shall be reduced by all holes (including window and door openings) exceeding 0.3 square meters. 骨架及板面的计算面积应扣除所有超过0.3平方米的洞孔（包括门窗洞口）。
C114: 2.4.4
D115: The unit price for all lightweight partition walls includes the following: 所有轻质隔墙的单价已包括下述内容：
D116: (1) Comprehensive cost of material transportation, shearing, cutting, installation, and painting.
D117: (2) Rivets, screws, expansion screws, and member pre-burials shall be included in the item.
D118: (3) Treatment of joint opening shall be included in the project of panel.
D119: (4) Additional materials, embedded parts and treatments required at the intersection with brick/concrete wall columns or floor slabs.
D120: (5) Cavity should include the system partition & door, movable partition (supporting steel frame rail is included in movable partition, provided by the manufacturer), etc. and the additional reinforcement of the top surface required for all costs.
D121: （1）材料运输、剪裁、割切、安装、油漆等综合费用。
D122: （2）铆钉、螺丝、膨胀螺丝、构件预埋件等均应包括在项目内。
D123: （3）接缝口之处理应包括在板面的项目内。
D124: （4）与砖/混凝土墙柱或楼板之交接处所需之额外物料、埋件及处理等。
D125: （5）调腔需包含系统隔断&门，活动隔断（配套钢架轨道含在活动隔断，由厂家自行提供）等与顶面额外加固所需一切费用
B127: 2.5 Glass partition and window works 玻璃隔断及窗工程
C129: 2.5.1
D130: All glass partitions shall be calculated in square meters by separate items according to different materials, and their thickness shall be indicated. 所有玻璃隔断应按材质不同分别立项以平方米计算，并注明其厚度。
C132: 2.5.2
D133: The calculated area of all glass partitions shall be deducted from all holes exceeding 0.3 square meters (including window and door openings). 所有玻璃隔断的计算面积应扣除所有超过0.3平方米的洞孔（包括门窗洞口）
C135: 2.5.3
D136: The unit price for all glass partitions includes the following 所有玻璃隔断的单价已包括下述内容：
D137: (1) The cost of glass and glass partition metal border.
D138: (2) Comprehensive costs of material transportation, cutting, loss, installation, etc.
D139: (3) Costs of rivets, screws, expansion screws, pre-embedded parts, sealing tape, sealant, etc., and installation of nails, screws, components and anti-rust treatment.
D140: (4) All the costs required for connection and fixing with the ground and the top surface
D141: (5) Costs of reinforcement and pre-burial for other installation items.
D142: (6) Costs for the treatment of joints and corner glass silicone corner guards, etc.
D143: (7) Costs of additional materials, embedded parts and treatments required at the junction with block/lightweight partition walls/concrete columns or floor slabs.
D144: (8) Costs for completing the curved shapes required in the drawings.
D145: (9) The cost of metal structure support, stainless steel fixing and fixing plate required in the drawings.
D146: (10) The cost of supplying, transporting, installing, cutting, wearing out, electric devices (if any) for the louvers between the double glazing.
D147: (11) All the costs required to complete other work required for the glass partition according to the drawings and technical specifications.
...

Sheet PER Budget
A1: PER Category | B1: Budget Amount (USD)
A2: Partitions (Drywall, Glazing etc.) | B2: 1185018.7
A3: Flooring Works (Fit-Out) | B3: 365437.82
A4: Joinery Works | B4: 790620.55
A5: Signage / Graphics | B5: 86030.488
A6: Carpet | B6: 418220.66
A7: Miscellaneous Items Works (Fit-Out Works) | B7: 1202460.9
A8: Fire Suppression Systems (Fit-Out Works) | B8: 539336.75
A9: Building Management Systems | B9: 182203.34
A10: Low Side Electrical Works | B10: 751300.1
A11: HVAC systems | B11: 1923047.7
A12: Dry Works & Wall Cladding | B12: 590870.66
A13: Ceiling (Fit Out) | B13: 733910.16
... A21: TOTAL | B21: 10087575

Sheet QS Estimation
A2: QS Estimate Category | B2: Total Amount (USD)
A3: Partitions (Drywall, Glazing etc.) | B3: 1260943.5
A4: HVAC systems | B4: 1993235
A5: Miscellaneous Items Works (Fit-Out Works) | B5: 1293264.6
A6: Ceiling (Fit Out) | B6: 776799.38
A7: Light Fixtures | B7: 628513.01
A8: Dry Works & Wall Cladding | B8: 625400.74
A9: Joinery Works | B9: 836823.89
A10: Low Side Electrical Works | B10: 782777.74
A11: Carpet | B11: 440330.88
A12: Flooring Works (Fit-Out) | B12: 384757.55
A13: Uninterruptible Power Supply (UPS) Works | B13: 12907.583
A14: Sprinkler Installations (Fit-Out Works) | B14: 231243.96
... A21: TOTAL CLASSIFIED | B21: 10614203

Sheet Vendor Quotation
A2: =Cover!A2 -> CHN, Shanghai Campus Building 1 RF Project
A3: =Cover!A3 -> Build General Contractor Works
A4: =Cover!A4 -> Issue Date:
A6: =Cover!A6 -> Name of Tenderer:__________________________________
A8: SUMMARY PAGE
C9: Vendor-A | D9: Vendor-B | E9: Vendor-C | F9: Vendor-D | G9: Vendor-E
A10: No. | B10: DESCRIPTION | C10: GC Total (USD) | D10: GC Total (USD) | E10: GC Total (USD) | F10: GC Total (USD) | G10: GC Total (USD)
B11: Preliminaries (inclusive of M&E Works)
A12: A | B12: Preliminaries (inclusive of M&E Works) | C12: 546846.37 | D12: 993728.83 | E12: 736323.59 | F12: 438585.14 | G12: 576012.57
B14: Fit out works 装饰工程
A15: B | B15: Demolition Works 拆除工程 | C15: 119849.1 | D15: 233860.7 | E15: 221826.44 | F15: 96871.504 | G15: 156184.22
A16: C | B16: Partition Works 隔墙工程 | C16: 849635.18 | D16: 821501.05 | E16: 1106511 | F16: 703315.33 | G16: 846904.06
A17: D | B17: Wall finish 墙面饰面 | C17: 417919.18 | D17: 602425.32 | E17: 445403.16 | F17: 690771.49 | G17: 555063.02
A18: E | B18: Ceiling Works 天花工程 | C18: 715053.73 | D18: 535674.71 | E18: 812038.92 | F18: 801011.75 | G18: 564639.68
A19: G | B19: Flooring Works (Fit-Out) 地面工程 | C19: 477632.44 | D19: 507127.22 | E19: 391893.22 | F19: 614742.41 | G19: 457736.03
A20: H | B20: Carpet 地毯工程 | C20: 625465.15 | D20: 461285.82 | E20: 445217.92 | F20: 885170.58 | G20: 429503.45
A21: I | B21: Door Works 门工程 | C21: 434751.24 | D21: 495751.05 | E21: 423645.21 | F21: 364999.16 | G21: 518448.87
A22: J | B22: Carpentry Works 木器工程 | C22: 375383.69 | D22: 307515.49 | E22: 254766.95 | F22: 239009.72 | G22: 144286.51
A23: K | B23: Internal Staircase 内部楼梯 | C23: 48233.678 | D23: 65832.754 | E23: 32710.704 | F23: 42976.893 | G23: 67681.166
A24: L | B24: Atrium works 中庭工程 | C24: 58127.264 | D24: 152019.42 | E24: 94501.447 | F24: 131542.08 | G24: 229863.88
A25: M | B25: Signage / Graphics 标识及图形 | C25: 36548.736 | D25: 17865.086 | E25: 96946.236 | F25: 13121.478 | G25: 20981.832
A26: N | B26: Blinds 窗帘 | C26: 62936.923 | D26: 44408.772 | E26: 160250.79 | F26: 21624.045 | G26: 36696.613
A27: O | B27: Miscellaneous Items Works 其他杂项 | C27: 378108.89 | D27: 190134.78 | E27: 118922.77 | F27: 131082.57 | G27: 149716.47
B29: MEP works 机电工程
A30: P | B30: Building Management Systems (BMS) | C30: 275672.88 | D30: 316095.32 | E30: 197395.69 | F30: 244799.37 | G30: 376965.88
A31: Q | B31: Low Side Electrical Works 低压电气 | C31: 1016195.7 | D31: 756933.66 | E31: 684190.8 | F31: 917038.8 | G31: 900709.43
A32: R | B32: Uninterruptible Power Supply (UPS) Works | C32: 25926.455 | D32: 22732.436 | E32: 15394.362 | F32: 22956.104 | G32: 26618.419
A33: S | B33: Light Fixtures 灯具 | C33: 949513.87 | D33: 958438.27 | E33: 556923.08 | F33: 854709.37 | G33: 927659.28
A34: T | B34: Lighting Management System 灯控系统 | C34: 417224.46 | D34: 296517.32 | E34: 242001.88 | F34: 381124.44 | G34: 412102.85
A35: U | B35: Air-conditioning Works 空调工程 | C35: 1996643.3 | D35: 2154309.9 | E35: 2055253.5 | F35: 2061141.9 | G35: 3061031
A36: V | B36: Fire Suppression Systems (Fit-Out Works) | C36: 198793.38 | D36: 298165.46 | E36: 507188.19 | F36: 352178.62 | G36: 222602.87
A37: W | B37: Sprinkler Installations (Fit-Out Works) | C37: 301032.6 | D37: 289370.52 | E37: 203774.63 | F37: 505131.24 | G37: 329130.74
A38: X | B38: Fire Suppression Systems 消防系统 | C38: 523126.85 | D38: 522838.19 | E38: 259842.41 | F38: 631662.65 | G38: 484655.71
A39: Y | B39: Plumbing & Drainage works 给排水系统 | C39: 71824.69 | D39: 148648.84 | E39: 114230.4 | F39: 115912.3 | G39: 132452.53
B41: Total | C41: 10922446 | D41: 11193181 | E41: 10177153 | F41: 11261479 | G41: 11627647

Sheet MAPPING RULES
A1: Vendor WBS Description | B1: PER-Budget / QS Estimate Category
A2: Preliminaries (inclusive of M&E Works) | B2: Miscellaneous Items Works (Fit-Out Works)
A3: Demolition Works 拆除工程 | B3: Miscellaneous Items Works (Fit-Out Works)
A4: Partition Works 隔墙工程 | B4: Partitions (Drywall, Glazing etc.)
A5: Wall finish 墙面饰面 | B5: Dry Works & Wall Cladding
A6: Ceiling Works 天花工程 | B6: Ceiling (Fit Out)
A7: Flooring Works (Fit-Out) 地面工程 | B7: Flooring Works (Fit-Out)
A8: Carpet 地毯工程 | B8: Carpet
A9: Door Works 门工程 | B9: Joinery Works
A10: Carpentry Works 木器工程 | B10: Joinery Works
A11: Internal Staircase 内部楼梯 | B11: Joinery Works
A12: Atrium works 中庭工程 | B12: Dry Works & Wall Cladding
... A25: Plumbing & Drainage works 给排水系统 | B25: Public Health Engineering (PHE) Works

Sheet Historical Unit Rates
A2: QS Category | B2: Historical Unit Rate (USD/Sqm)
A3: Partitions (Drywall, Glazing etc.) | B3: 295.20901
A4: HVAC systems | B4: 475.84638
A5: Miscellaneous Items Works (Fit-Out Works) | B5: 300.68782
A6: Ceiling (Fit Out) | B6: 184.19163
A7: Light Fixtures | B7: 143.81158
A8: Dry Works & Wall Cladding | B8: 150.31213
A9: Joinery Works | B9: 195.33609
A10: Low Side Electrical Works | B10: 185.24809
A11: Carpet | B11: 103.39388
A12: Flooring Works (Fit-Out) | B12: 89.279768
A13: Uninterruptible Power Supply (UPS) Works | B13: 3.0665502
A14: Sprinkler Installations (Fit-Out Works) | B14: 56.271796
... A22: Weighted Average Unit Rate | B22: 2500

Sheet HYE新增项
A2: Bill of Quantity for Build General Contractor Works
A3: =[40]Summary!A2 -> CHN, Shanghai Campus Building 1 RF Project
A4: =[40]Summary!A4 -> Issue Date: 2026/08/04
A6: =[40]Summary!A6 -> Name of Tenderer:___HYE_________________________________
A8: DO NOT change the form of this Schdule of Rates, any changes or ideas please use "Please specify" rows 不要自行更改或修改表格格式，任何改动需使用”请列明“行
A10: No. 序号 | B10: DESCRIPTION OF WORKS 描述 | C10: Material Code 材料编号 | D10: Spec.Brand 品牌型号 | E10: Refer. Quantity/参考数量 | T10: Tender Quantity/ 投标数量 | AI10: Unit 单位 | AJ10: Unit Rate(¥) 单价 | AM10: Total(RMB)/ 合计 | AU10: Total(RMB)/ 合计 | BB10: Remarks 备注
E11: Phase 1 短翼 | M11: Phase 2 长翼 | T11: Phase 1 短翼 | AB11: Phase 2 长翼 | AJ11: Labor | AK11: Material | AL11: Total | AM11: Phase 1 短翼 | AU11: Phase 2 长翼
E12: -1F | F12: 1F | G12: 2F | H12: 3F | I12: 4F | J12: 5F | K12: Roof | L12: Total | M12: 1F | N12: 2F | O12: 3F | P12: 4F | Q12: 5F | R12: Roof | S12: Total | T12: -1F | U12: 1F | V12: 2F | W12: 3F | X12: 4F | Y12: 5F | Z12: Roof | AA12: Total | AB12: 1F | AC12: 2F | AD12: 3F | AE12: 4F | AF12: 5F | AG12: Roof | AH12: Total | AJ12: 人工 | AK12: 材料 | AL12: 小计 | AM12: -1F | AN12: 1F | AO12: 2F | AP12: 3F | AQ12: 4F | AR12: 5F | AS12: Roof | AT12: Total | AU12: 1F | AV12: 2F | AW12: 3F | AX12: 4F | AY12: 5F | AZ12: Roof | BA12: Total
A13: L | B13: Electrical Works 强电工程
A14: 1 | B14: 提供安装配电箱 RAPRBH4 | Z14: 1 | AA14: =SUM(T14:Z14) -> 1 | AH14: =SUM(AB14:AG14) -> 0 | AI14: set | AJ14: 950 | AK14: 11400 | AL14: =AJ14+AK14 -> 12350 | AM14: =T14*AL14 -> 0 | AN14: =U14*AL14 -> 0 | AO14: =V14*AL14 -> 0 | AP14: =W14*AL14 -> 0 | AQ14: =X14*AL14 -> 0 | AR14: =Y14*AL14 -> 0 | AS14: =Z14*AL14 -> 12350 | AT14: =SUM(AM14:AS14) -> 12350 | AU14: =AB14*AL14 -> 0 | AV14: =AC14*AL14 -> 0 | AW14: =AD14*AL14 -> 0 | AX14: =AE14*AL14 -> 0 | AY14: =AF14*AL14 -> 0 | AZ14: =AG14*AL14 -> 0 | BA14: =SUM(AU14:AZ14) -> 0
A15: 2 | B15: 配电箱改造 1AP2-1 | U15: 1 | AA15: =SUM(T15:Z15) -> 1 | AH15: =SUM(AB15:AG15) -> 0 | AI15: set | AJ15: 1100 | AK15: 600 | AL15: =AJ15+AK15 -> 1700 | AM15: =T15*AL15 -> 0 | AN15: =U15*AL15 -> 1700 | AO15: =V15*AL15 -> 0 | AP15: =W15*AL15 -> 0 | AQ15: =X15*AL15 -> 0 | AR15: =Y15*AL15 -> 0 | AS15: =Z15*AL15 -> 0 | AT15: =SUM(AM15:AS15) -> 1700 | AU15: =AB15*AL15 -> 0 | AV15: =AC15*AL15 -> 0 | AW15: =AD15*AL15 -> 0 | AX15: =AE15*AL15 -> 0 | AY15: =AF15*AL15 -> 0 | AZ15: =AG15*AL15 -> 0 | BA15: =SUM(AU15:AZ15) -> 0
A16: 3 | B16: 配电箱改造 2ATit1 | V16: 1 | AA16: =SUM(T16:Z16) -> 1 | AH16: =SUM(AB16:AG16) -> 0 | AI16: set | AJ16: 1100 | AK16: 600 | AL16: =AJ16+AK16 -> 1700 | AM16: =T16*AL16 -> 0 | AN16: =U16*AL16 -> 0 | AO16: =V16*AL16 -> 1700 | AP16: =W16*AL16 -> 0 | AQ16: =X16*AL16 -> 0 | AR16: =Y16*AL16 -> 0 | AS16: =Z16*AL16 -> 0 | AT16: =SUM(AM16:AS16) -> 1700 | AU16: =AB16*AL16 -> 0 | AV16: =AC16*AL16 -> 0 | AW16: =AD16*AL16 -> 0 | AX16: =AE16*AL16 -> 0 | AY16: =AF16*AL16 -> 0 | AZ16: =AG16*AL16 -> 0 | BA16: =SUM(AU16:AZ16) -> 0
A17: 4 | B17: 配电箱改造 UPS31-1 | U17: 1 | AA17: =SUM(T17:Z17) -> 1 | AH17: =SUM(AB17:AG17) -> 0 | AI17: set | AJ17: 1100 | AK17: 2400 | AL17: =AJ17+AK17 -> 3500 | AM17: =T17*AL17 -> 0 | AN17: =U17*AL17 -> 3500 | AO17: =V17*AL17 -> 0 | AP17: =W17*AL17 -> 0 | AQ17: =X17*AL17 -> 0 | AR17: =Y17*AL17 -> 0 | AS17: =Z17*AL17 -> 0 | AT17: =SUM(AM17:AS17) -> 3500 | AU17: =AB17*AL17 -> 0 | AV17: =AC17*AL17 -> 0 | AW17: =AD17*AL17 -> 0 | AX17: =AE17*AL17 -> 0 | AY17: =AF17*AL17 -> 0 | AZ17: =AG17*AL17 -> 0 | BA17: =SUM(AU17:AZ17) -> 0
A18: 5 | B18: 配电箱改造 UPS51-1 | U18: 1 | AA18: =SUM(T18:Z18) -> 1 | AH18: =SUM(AB18:AG18) -> 0 | AI18: set | AJ18: 1100 | AK18: 2400 | AL18: =AJ18+AK18 -> 3500 | AM18: =T18*AL18 -> 0 | AN18: =U18*AL18 -> 3500 | AO18: =V18*AL18 -> 0 | AP18: =W18*AL18 -> 0 | AQ18: =X18*AL18 -> 0 | AR18: =Y18*AL18 -> 0 | AS18: =Z18*AL18 -> 0 | AT18: =SUM(AM18:AS18) -> 3500 | AU18: =AB18*AL18 -> 0 | AV18: =AC18*AL18 -> 0 | AW18: =AD18*AL18 -> 0 | AX18: =AE18*AL18 -> 0 | AY18: =AF18*AL18 -> 0 | AZ18: =AG18*AL18 -> 0 | BA18: =SUM(AU18:AZ18) -> 0
A19: 6 | B19: 模块式风冷热泵隔离开关箱 | Z19: 18 | AA19: =SUM(T19:Z19) -> 18 | AH19: =SUM(AB19:AG19) -> 0 | AI19: set | AJ19: 1100 | AK19: 10200 | AL19: =AJ19+AK19 -> 11300 | AM19: =T19*AL19 -> 0 | AN19: =U19*AL19 -> 0 | AO19: =V19*AL19 -> 0 | AP19: =W19*AL19 -> 0 | AQ19: =X19*AL19 -> 0 | AR19: =Y19*AL19 -> 0 | AS19: =Z19*AL19 -> 203400 | AT19: =SUM(AM19:AS19) -> 203400 | AU19: =AB19*AL19 -> 0 | AV19: =AC19*AL19 -> 0 | AW19: =AD19*AL19 -> 0 | AX19: =AE19*AL19 -> 0 | AY19: =AF19*AL19 -> 0 | AZ19: =AG19*AL19 -> 0 | BA19: =SUM(AU19:AZ19) -> 0
A20: 7 | B20: WDZB-YJY-4x120+1x95 | Z20: 1680 | AA20: =SUM(T20:Z20) -> 1680 | AH20: =SUM(AB20:AG20) -> 0 | AI20: m | AJ20: 85 | AK20: 792 | AL20: =AJ20+AK20 -> 877 | AM20: =T20*AL20 -> 0 | AN20: =U20*AL20 -> 0 | AO20: =V20*AL20 -> 0 | AP20: =W20*AL20 -> 0 | AQ20: =X20*AL20 -> 0 | AR20: =Y20*AL20 -> 0 | AS20: =Z20*AL20 -> 1473360 | AT20: =SUM(AM20:AS20) -> 1473360 | AU20: =AB20*AL20 -> 0 | AV20: =AC20*AL20 -> 0 | AW20: =AD20*AL20 -> 0 | AX20: =AE20*AL20 -> 0 | AY20: =AF20*AL20 -> 0 | AZ20: =AG20*AL20 -> 0 | BA20: =SUM(AU20:AZ20) -> 0
A21: 8 | B21: WDZB-YJY-3x70 | Z21: 228 | AA21: =SUM(T21:Z21) -> 228 | AH21: =SUM(AB21:AG21) -> 0 | AI21: m | AJ21: 42 | AK21: 286 | AL21: =AJ21+AK21 -> 328 | AM21: =T21*AL21 -> 0 | AN21: =U21*AL21 -> 0 | AO21: =V21*AL21 -> 0 | AP21: =W21*AL21 -> 0 | AQ21: =X21*AL21 -> 0 | AR21: =Y21*AL21 -> 0 | AS21: =Z21*AL21 -> 74784 | AT21: =SUM(AM21:AS21) -> 74784 | AU21: =AB21*AL21 -> 0 | AV21: =AC21*AL21 -> 0 | AW21: =AD21*AL21 -> 0 | AX21: =AE21*AL21 -> 0 | AY21: =AF21*AL21 -> 0 | AZ21: =AG21*AL21 -> 0 | BA21: =SUM(AU21:AZ21) -> 0
A22: 9 | B22: WDZB-YJY-3x16+1x16 | Z22: 62 | AA22: =SUM(T22:Z22) -> 62 | AH22: =SUM(AB22:AG22) -> 0 | AI22: m | AJ22: 24 | AK22: 90 | AL22: =AJ22+AK22 -> 114 | AM22: =T22*AL22 -> 0 | AN22: =U22*AL22 -> 0 | AO22: =V22*AL22 -> 0 | AP22: =W22*AL22 -> 0 | AQ22: =X22*AL22 -> 0 | AR22: =Y22*AL22 -> 0 | AS22: =Z22*AL22 -> 7068 | AT22: =SUM(AM22:AS22) -> 7068 | AU22: =AB22*AL22 -> 0 | AV22: =AC22*AL22 -> 0 | AW22: =AD22*AL22 -> 0 | AX22: =AE22*AL22 -> 0 | AY22: =AF22*AL22 -> 0 | AZ22: =AG22*AL22 -> 0 | BA22: =SUM(AU22:AZ22) -> 0
A23: 10 | B23: WDZB-YJY-3x10+1x10 | Z23: 22 | AA23: =SUM(T23:Z23) -> 22 | AH23: =SUM(AB23:AG23) -> 0 | AI23: m | AJ23: 19 | AK23: 57.4 | AL23: =AJ23+AK23 -> 76.4 | AM23: =T23*AL23 -> 0 | AN23: =U23*AL23 -> 0 | AO23: =V23*AL23 -> 0 | AP23: =W23*AL23 -> 0 | AQ23: =X23*AL23 -> 0 | AR23: =Y23*AL23 -> 0 | AS23: =Z23*AL23 -> 1680.8 | AT23: =SUM(AM23:AS23) -> 1680.8 | AU23: =AB23*AL23 -> 0 | AV23: =AC23*AL23 -> 0 | AW23: =AD23*AL23 -> 0 | AX23: =AE23*AL23 -> 0 | AY23: =AF23*AL23 -> 0 | AZ23: =AG23*AL23 -> 0 | BA23: =SUM(AU23:AZ23) -> 0
A24: 11 | B24: WDZB-YJY-3x6+1x6 | Z24: 40 | AA24: =SUM(T24:Z24) -> 40 | AH24: =SUM(AB24:AG24) -> 0 | AI24: m | AJ24: 12 | AK24: 35.5 | AL24: =AJ24+AK24 -> 47.5 | AM24: =T24*AL24 -> 0 | AN24: =U24*AL24 -> 0 | AO24: =V24*AL24 -> 0 | AP24: =W24*AL24 -> 0 | AQ24: =X24*AL24 -> 0 | AR24: =Y24*AL24 -> 0 | AS24: =Z24*AL24 -> 1900 | AT24: =SUM(AM24:AS24) -> 1900 | AU24: =AB24*AL24 -> 0 | AV24: =AC24*AL24 -> 0 | AW24: =AD24*AL24 -> 0 | AX24: =AE24*AL24 -> 0 | AY24: =AF24*AL24 -> 0 | AZ24: =AG24*AL24 -> 0 | BA24: =SUM(AU24:AZ24) -> 0
A25: 12 | B25: 提供及安装ISP1装饰吊灯 | U25: 5 | W25: 2 | AA25: =SUM(T25:Z25) -> 7 | AH25: =SUM(AB25:AG25) -> 0 | AI25: set | AJ25: 180 | AK25: 5400 | AL25: =AJ25+AK25 -> 5580 | AM25: =T25*AL25 -> 0 | AN25: =U25*AL25 -> 27900 | AO25: =V25*AL25 -> 0 | AP25: =W25*AL25 -> 11160 | AQ25: =X25*AL25 -> 0 | AR25: =Y25*AL25 -> 0 | AS25: =Z25*AL25 -> 0 | AT25: =SUM(AM25:AS25) -> 39060 | AU25: =AB25*AL25 -> 0 | AV25: =AC25*AL25 -> 0 | AW25: =AD25*AL25 -> 0 | AX25: =AE25*AL25 -> 0 | AY25: =AF25*AL25 -> 0 | AZ25: =AG25*AL25 -> 0 | BA25: =SUM(AU25:AZ25) -> 0
A26: 13 | B26: 提供及安装USB插座 | U26: 9 | V26: 6 | W26: 14 | X26: 8 | Y26: 11 | AA26: =SUM(T26:Z26) -> 48 | AB26: 15 | AC26: 21 | AD26: 21 | AE26: 22 | AF26: 12 | AH26: =SUM(AB26:AG26) -> 91 | AI26: set | AJ26: 110 | AK26: 160 | AL26: =AJ26+AK26 -> 270 | AM26: =T26*AL26 -> 0 | AN26: =U26*AL26 -> 2430 | AO26: =V26*AL26 -> 1620 | AP26: =W26*AL26 -> 3780 | AQ26: =X26*AL26 -> 2160 | AR26: =Y26*AL26 -> 2970 | AS26: =Z26*AL26 -> 0 | AT26: =SUM(AM26:AS26) -> 12960 | AU26: =AB26*AL26 -> 4050 | AV26: =AC26*AL26 -> 5670 | AW26: =AD26*AL26 -> 5670 | AX26: =AE26*AL26 -> 5940 | AY26: =AF26*AL26 -> 3240 | AZ26: =AG26*AL26 -> 0 | BA26: =SUM(AU26:AZ26) -> 24570
A27: 14 | B27: 提供及安装设备出线点位 | U27: 15 | V27: 18 | W27: 19 | X27: 19 | Y27: 23 | AA27: =SUM(T27:Z27) -> 94 | AB27: 27 | AC27: 27 | AD27: 30 | AE27: 29 | AF27: 21 | AH27: =SUM(AB27:AG27) -> 134 | AI27: set | AJ27: 180 | AK27: 180 | AL27: =AJ27+AK27 -> 360 | AM27: =T27*AL27 -> 0 | AN27: =U27*AL27 -> 5400 | AO27: =V27*AL27 -> 6480 | AP27: =W27*AL27 -> 6840 | AQ27: =X27*AL27 -> 6840 | AR27: =Y27*AL27 -> 8280 | AS27: =Z27*AL27 -> 0 | AT27: =SUM(AM27:AS27) -> 33840 | AU27: =AB27*AL27 -> 9720 | AV27: =AC27*AL27 -> 9720 | AW27: =AD27*AL27 -> 10800 | AX27: =AE27*AL27 -> 10440 | AY27: =AF27*AL27 -> 7560 | AZ27: =AG27*AL27 -> 0 | BA27: =SUM(AU27:AZ27) -> 48240
A28: 15 | B28: 提供及安装风机盘管线控管道 | U28: 59 | V28: 53 | W28: 75 | X28: 53 | Y28: 75 | AA28: =SUM(T28:Z28) -> 315 | AB28: 52 | AC28: 54 | AD28: 65 | AE28: 57 | AF28: 65 | AH28: =SUM(AB28:AG28) -> 293 | AI28: set | AJ28: 70 | AK28: 75 | AL28: =AJ28+AK28 -> 145 | AM28: =T28*AL28 -> 0 | AN28: =U28*AL28 -> 8555 | AO28: =V28*AL28 -> 7685 | AP28: =W28*AL28 -> 10875 | AQ28: =X28*AL28 -> 7685 | AR28: =Y28*AL28 -> 10875 | AS28: =Z28*AL28 -> 0 | AT28: =SUM(AM28:AS28) -> 45675 | AU28: =AB28*AL28 -> 7540 | AV28: =AC28*AL28 -> 7830 | AW28: =AD28*AL28 -> 9425 | AX28: =AE28*AL28 -> 8265 | AY28: =AF28*AL28 -> 9425 | AZ28: =AG28*AL28 -> 0 | BA28: =SUM(AU28:AZ28) -> 42485
A29: 16 | B29: 提供及安装卷闸门电源 | U29: 1 | V29: 5 | W29: 7 | X29: 6 | Y29: 7 | AA29: =SUM(T29:Z29) -> 26 | AC29: 4 | AD29: 2 | AE29: 4 | AF29: 3 | AH29: =SUM(AB29:AG29) -> 13 | AI29: set | AJ29: 390 | AK29: 390 | AL29: =AJ29+AK29 -> 780 | AM29: =T29*AL29 -> 0 | AN29: =U29*AL29 -> 780 | AO29: =V29*AL29 -> 3900 | AP29: =W29*AL29 -> 5460 | AQ29: =X29*AL29 -> 4680 | AR29: =Y29*AL29 -> 5460 | AS29: =Z29*AL29 -> 0 | AT29: =SUM(AM29:AS29) -> 20280 | AU29: =AB29*AL29 -> 0 | AV29: =AC29*AL29 -> 3120 | AW29: =AD29*AL29 -> 1560 | AX29: =AE29*AL29 -> 3120 | AY29: =AF29*AL29 -> 2340 | AZ29: =AG29*AL29 -> 0 | BA29: =SUM(AU29:AZ29) -> 10140
A30: 17 | B30: 提供及安装天花强电桥架200*100 | U30: 158 | V30: 158 | W30: 158 | X30: 158 | Y30: 158 | AA30: =SUM(T30:Z30) -> 790 | AB30: 168 | AC30: 180 | AD30: 180 | AE30: 180 | AF30: 180 | AH30: =SUM(AB30:AG30) -> 888 | AI30: set | AJ30: 50 | AK30: 55 | AL30: =AJ30+AK30 -> 105 | AM30: =T30*AL30 -> 0 | AN30: =U30*AL30 -> 16590 | AO30: =V30*AL30 -> 16590 | AP30: =W30*AL30 -> 16590 | AQ30: =X30*AL30 -> 16590 | AR30: =Y30*AL30 -> 16590 | AS30: =Z30*AL30 -> 0 | AT30: =SUM(AM30:AS30) -> 82950 | AU30: =AB30*AL30 -> 17640 | AV30: =AC30*AL30 -> 18900 | AW30: =AD30*AL30 -> 18900 | AX30: =AE30*AL30 -> 18900 | AY30: =AF30*AL30 -> 18900 | AZ30: =AG30*AL30 -> 0 | BA30: =SUM(AU30:AZ30) -> 93240
A31: 18 | B31: 提供及安装地面强电桥架300*100 | U31: 175 | V31: 175 | W31: 205 | X31: 175 | Y31: 150 | AA31: =SUM(T31:Z31) -> 880 | AB31: 165 | AC31: 165 | AD31: 196 | AE31: 170 | AF31: 157 | AH31: =SUM(AB31:AG31) -> 853 | AI31: set | AJ31: 60 | AK31: 65 | AL31: =AJ31+AK31 -> 125 | AM31: =T31*AL31 -> 0 | AN31: =U31*AL31 -> 21875 | AO31: =V31*AL31 -> 21875 | AP31: =W31*AL31 -> 25625 | AQ31: =X31*AL31 -> 21875 | AR31: =Y31*AL31 -> 18750 | AS31: =Z31*AL31 -> 0 | AT31: =SUM(AM31:AS31) -> 110000 | AU31: =AB31*AL31 -> 20625 | AV31: =AC31*AL31 -> 20625 | AW31: =AD31*AL31 -> 24500 | AX31: =AE31*AL31 -> 21250 | AY31: =AF31*AL31 -> 19625 | AZ31: =AG31*AL31 -> 0 | BA31: =SUM(AU31:AZ31) -> 106625
A32: 19 | B32: 安装双鉴占用传感器管道 | U32: 41 | V32: 41 | W32: 47 | X32: 42 | Y32: 46 | AA32: =SUM(T32:Z32) -> 217 | AB32: 48 | AC32: 56 | AD32: 58 | AE32: 59 | AF32: 39 | AH32: =SUM(AB32:AG32) -> 260 | AI32: m | AJ32: 90 | AK32: 90 | AL32: =AJ32+AK32 -> 180 | AM32: =T32*AL32 -> 0 | AN32: =U32*AL32 -> 7380 | AO32: =V32*AL32 -> 7380 | AP32: =W32*AL32 -> 8460 | AQ32: =X32*AL32 -> 7560 | AR32: =Y32*AL32 -> 8280 | AS32: =Z32*AL32 -> 0 | AT32: =SUM(AM32:AS32) -> 39060 | AU32: =AB32*AL32 -> 8640 | AV32: =AC32*AL32 -> 10080 | AW32: =AD32*AL32 -> 10440 | AX32: =AE32*AL32 -> 10620 | AY32: =AF32*AL32 -> 7020 | AZ32: =AG32*AL32 -> 0 | BA32: =SUM(AU32:AZ32) -> 46800
A33: 20 | B33: 安装室外照度传感器管道 | U33: 6 | V33: 9 | W33: 11 | X33: 9 | Y33: 14 | AA33: =SUM(T33:Z33) -> 49 | AB33: 7 | AC33: 9 | AD33: 9 | AE33: 9 | AF33: 9 | AH33: =SUM(AB33:AG33) -> 43 | AI33: m | AJ33: 90 | AK33: 90 | AL33: =AJ33+AK33 -> 180 | AM33: =T33*AL33 -> 0 | AN33: =U33*AL33 -> 1080 | AO33: =V33*AL33 -> 1620 | AP33: =W33*AL33 -> 1980 | AQ33: =X33*AL33 -> 1620 | AR33: =Y33*AL33 -> 2520 | AS33: =Z33*AL33 -> 0 | AT33: =SUM(AM33:AS33) -> 8820 | AU33: =AB33*AL33 -> 1260 | AV33: =AC33*AL33 -> 1620 | AW33: =AD33*AL33 -> 1620 | AX33: =AE33*AL33 -> 1620 | AY33: =AF33*AL33 -> 1620 | AZ33: =AG33*AL33 -> 0 | BA33: =SUM(AU33:AZ33) -> 7740
A34: 21 | B34: 安装室内照度传感器管道 | U34: 25 | V34: 26 | W34: 29 | X34: 29 | Y34: 26 | AA34: =SUM(T34:Z34) -> 135 | AB34: 30 | AC34: 33 | AD34: 37 | AE34: 34 | AF34: 25 | AH34: =SUM(AB34:AG34) -> 159 | AI34: m | AJ34: 90 | AK34: 90 | AL34: =AJ34+AK34 -> 180 | AM34: =T34*AL34 -> 0 | AN34: =U34*AL34 -> 4500 | AO34: =V34*AL34 -> 4680 | AP34: =W34*AL34 -> 5220 | AQ34: =X34*AL34 -> 5220 | AR34: =Y34*AL34 -> 4680 | AS34: =Z34*AL34 -> 0 | AT34: =SUM(AM34:AS34) -> 24300 | AU34: =AB34*AL34 -> 5400 | AV34: =AC34*AL34 -> 5940 | AW34: =AD34*AL34 -> 6660 | AX34: =AE34*AL34 -> 6120 | AY34: =AF34*AL34 -> 4500 | AZ34: =AG34*AL34 -> 0 | BA34: =SUM(AU34:AZ34) -> 28620
A35: 22 | B35: 安装厂景控制面板管道 | U35: 50 | V35: 40 | W35: 46 | X35: 41 | Y35: 46 | AA35: =SUM(T35:Z35) -> 223 | AB35: 48 | AC35: 56 | AD35: 58 | AE35: 59 | AF35: 39 | AH35: =SUM(AB35:AG35) -> 260 | AI35: m | AJ35: 90 | AK35: 90 | AL35: =AJ35+AK35 -> 180 | AM35: =T35*AL35 -> 0 | AN35: =U35*AL35 -> 9000 | AO35: =V35*AL35 -> 7200 | AP35: =W35*AL35 -> 8280 | AQ35: =X35*AL35 -> 7380 | AR35: =Y35*AL35 -> 8280 | AS35: =Z35*AL35 -> 0 | AT35: =SUM(AM35:AS35) -> 40140 | AU35: =AB35*AL35 -> 8640 | AV35: =AC35*AL35 -> 10080 | AW35: =AD35*AL35 -> 10440 | AX35: =AE35*AL35 -> 10620 | AY35: =AF35*AL35 -> 7020 | AZ35: =AG35*AL35 -> 0 | BA35: =SUM(AU35:AZ35) -> 46800
A36: 23 | B36: 提供及安装BMS管道 | U36: 243 | V36: 191 | W36: 238 | X36: 205 | Y36: 194 | AA36: =SUM(T36:Z36) -> 1071 | AB36: 203 | AC36: 197 | AD36: 203 | AE36: 193 | AF36: 208 | AH36: =SUM(AB36:AG36) -> 1004 | AI36: m | AJ36: 85 | AK36: 85 | AL36: =AJ36+AK36 -> 170 | AM36: =T36*AL36 -> 0 | AN36: =U36*AL36 -> 41310 | AO36: =V36*AL36 -> 32470 | AP36: =W36*AL36 -> 40460 | AQ36: =X36*AL36 -> 34850 | AR36: =Y36*AL36 -> 32980 | AS36: =Z36*AL36 -> 0 | AT36: =SUM(AM36:AS36) -> 182070 | AU36: =AB36*AL36 -> 34510 | AV36: =AC36*AL36 -> 33490 | AW36: =AD36*AL36 -> 34510 | AX36: =AE36*AL36 -> 32810 | AY36: =AF36*AL36 -> 35360 | AZ36: =AG36*AL36 -> 0 | BA36: =SUM(AU36:AZ36) -> 170680
A37: 24 | B37: 提供及安装地面电子 风口电源 | U37: 140 | V37: 99 | W37: 117 | X37: 99 | Y37: 96 | AA37: =SUM(T37:Z37) -> 551 | AB37: 78 | AC37: 97 | AD37: 91 | AE37: 89 | AF37: 96 | AH37: =SUM(AB37:AG37) -> 451 | AI37: m | AJ37: 90 | AK37: 90 | AL37: =AJ37+AK37 -> 180 | AM37: =T37*AL37 -> 0 | AN37: =U37*AL37 -> 25200 | AO37: =V37*AL37 -> 17820 | AP37: =W37*AL37 -> 21060 | AQ37: =X37*AL37 -> 17820 | AR37: =Y37*AL37 -> 17280 | AS37: =Z37*AL37 -> 0 | AT37: =SUM(AM37:AS37) -> 99180 | AU37: =AB37*AL37 -> 14040 | AV37: =AC37*AL37 -> 17460 | AW37: =AD37*AL37 -> 16380 | AX37: =AE37*AL37 -> 16020 | AY37: =AF37*AL37 -> 17280 | AZ37: =AG37*AL37 -> 0 | BA37: =SUM(AU37:AZ37) -> 81180
A38: 25 | B38: 提供及安装电子风口控制线管道 | U38: 140 | V38: 99 | W38: 117 | X38: 99 | Y38: 96 | AA38: =SUM(T38:Z38) -> 551 | AB38: 78 | AC38: 97 | AD38: 91 | AE38: 89 | AF38: 96 | AH38: =SUM(AB38:AG38) -> 451 | AI38: m | AJ38: 70 | AK38: 75 | AL38: =AJ38+AK38 -> 145 | AM38: =T38*AL38 -> 0 | AN38: =U38*AL38 -> 20300 | AO38: =V38*AL38 -> 14355 | AP38: =W38*AL38 -> 16965 | AQ38: =X38*AL38 -> 14355 | AR38: =Y38*AL38 -> 13920 | AS38: =Z38*AL38 -> 0 | AT38: =SUM(AM38:AS38) -> 79895 | AU38: =AB38*AL38 -> 11310 | AV38: =AC38*AL38 -> 14065 | AW38: =AD38*AL38 -> 13195 | AX38: =AE38*AL38 -> 12905 | AY38: =AF38*AL38 -> 13920 | AZ38: =AG38*AL38 -> 0 | BA38: =SUM(AU38:AZ38) -> 65395
A39: 26 | B39: 提供及安装天花弱电桥架200*100 | U39: 170 | V39: 170 | W39: 170 | X39: 170 | Y39: 170 | AA39: =SUM(T39:Z39) -> 850 | AB39: 170 | AC39: 170 | AD39: 170 | AE39: 170 | AF39: 170 | AH39: =SUM(AB39:AG39) -> 850 | AI39: m | AJ39: 50 | AK39: 55 | AL39: =AJ39+AK39 -> 105 | AM39: =T39*AL39 -> 0 | AN39: =U39*AL39 -> 17850 | AO39: =V39*AL39 -> 17850 | AP39: =W39*AL39 -> 17850 | AQ39: =X39*AL39 -> 17850 | AR39: =Y39*AL39 -> 17850 | AS39: =Z39*AL39 -> 0 | AT39: =SUM(AM39:AS39) -> 89250 | AU39: =AB39*AL39 -> 17850 | AV39: =AC39*AL39 -> 17850 | AW39: =AD39*AL39 -> 17850 | AX39: =AE39*AL39 -> 17850 | AY39: =AF39*AL39 -> 17850 | AZ39: =AG39*AL39 -> 0 | BA39: =SUM(AU39:AZ39) -> 89250
A40: 27 | B40: 提供及安装地面弱电桥架400*50 | U40: 180 | V40: 180 | W40: 180 | X40: 180 | Y40: 180 | AA40: =SUM(T40:Z40) -> 900 | AB40: 180 | AC40: 180 | AD40: 180 | AE40: 180 | AF40: 180 | AH40: =SUM(AB40:AG40) -> 900 | AI40: m | AJ40: 65 | AK40: 70 | AL40: =AJ40+AK40 -> 135 | AM40: =T40*AL40 -> 0 | AN40: =U40*AL40 -> 24300 | AO40: =V40*AL40 -> 24300 | AP40: =W40*AL40 -> 24300 | AQ40: =X40*AL40 -> 24300 | AR40: =Y40*AL40 -> 24300 | AS40: =Z40*AL40 -> 0 | AT40: =SUM(AM40:AS40) -> 121500 | AU40: =AB40*AL40 -> 24300 | AV40: =AC40*AL40 -> 24300 | AW40: =AD40*AL40 -> 24300 | AX40: =AE40*AL40 -> 24300 | AY40: =AF40*AL40 -> 24300 | AZ40: =AG40*AL40 -> 0 | BA40: =SUM(AU40:AZ40) -> 121500
A41: 28 | B41: Supply and install intelligent lighting system 提供及安装智能照明系统 | AA41: =SUM(T41:Z41) -> 0 | AH41: =SUM(AB41:AG41) -> 0 | AL41: =AJ41+AK41 -> 0 | AM41: =T41*AL41 -> 0 | AN41: =U41*AL41 -> 0 | AO41: =V41*AL41 -> 0 | AP41: =W41*AL41 -> 0 | AQ41: =X41*AL41 -> 0 | AR41: =Y41*AL41 -> 0 | AS41: =Z41*AL41 -> 0 | AT41: =SUM(AM41:AS41) -> 0 | AU41: =AB41*AL41 -> 0 | AV41: =AC41*AL41 -> 0 | AW41: =AD41*AL41 -> 0 | AX41: =AE41*AL41 -> 0 | AY41: =AF41*AL41 -> 0 | AZ41: =AG41*AL41 -> 0 | BA41: =SUM(AU41:AZ41) -> 0
A42: 29 | B42: IP通讯网关模块 | U42: 1 | V42: 1 | W42: 1 | X42: 1 | Y42: 1 | AA42: =SUM(T42:Z42) -> 5 | AB42: 1 | AC42: 1 | AD42: 1 | AE42: 1 | AF42: 1 | AH42: =SUM(AB42:AG42) -> 5 | AI42: nos | AK42: 7850 | AL42: =AJ42+AK42 -> 7850 | AM42: =T42*AL42 -> 0 | AN42: =U42*AL42 -> 7850 | AO42: =V42*AL42 -> 7850 | AP42: =W42*AL42 -> 7850 | AQ42: =X42*AL42 -> 7850 | AR42: =Y42*AL42 -> 7850 | AS42: =Z42*AL42 -> 0 | AT42: =SUM(AM42:AS42) -> 39250 | AU42: =AB42*AL42 -> 7850 | AV42: =AC42*AL42 -> 7850 | AW42: =AD42*AL42 -> 7850 | AX42: =AE42*AL42 -> 7850 | AY42: =AF42*AL42 -> 7850 | AZ42: =AG42*AL42 -> 0 | BA42: =SUM(AU42:AZ42) -> 39250
A43: 30 | B43: 系统电源模块 | U43: 5 | V43: 5 | W43: 5 | X43: 5 | Y43: 5 | AA43: =SUM(T43:Z43) -> 25 | AB43: 5 | AC43: 5 | AD43: 5 | AE43: 5 | AF43: 5 | AH43: =SUM(AB43:AG43) -> 25 | AI43: nos | AK43: 4120 | AL43: =AJ43+AK43 -> 4120 | AM43: =T43*AL43 -> 0 | AN43: =U43*AL43 -> 20600 | AO43: =V43*AL43 -> 20600 | AP43: =W43*AL43 -> 20600 | AQ43: =X43*AL43 -> 20600 | AR43: =Y43*AL43 -> 20600 | AS43: =Z43*AL43 -> 0 | AT43: =SUM(AM43:AS43) -> 103000 | AU43: =AB43*AL43 -> 20600 | AV43: =AC43*AL43 -> 20600 | AW43: =AD43*AL43 -> 20600 | AX43: =AE43*AL43 -> 20600 | AY43: =AF43*AL43 -> 20600 | AZ43: =AG43*AL43 -> 0 | BA43: =SUM(AU43:AZ43) -> 103000
A44: 31 | B44: 线路/支线耦合器 | U44: 4 | V44: 4 | W44: 4 | X44: 4 | Y44: 4 | AA44: =SUM(T44:Z44) -> 20 | AB44: 4 | AC44: 4 | AD44: 4 | AE44: 4 | AF44: 4 | AH44: =SUM(AB44:AG44) -> 20 | AI44: nos | AK44: 5300 | AL44: =AJ44+AK44 -> 5300 | AM44: =T44*AL44 -> 0 | AN44: =U44*AL44 -> 21200 | AO44: =V44*AL44 -> 21200 | AP44: =W44*AL44 -> 21200 | AQ44: =X44*AL44 -> 21200 | AR44: =Y44*AL44 -> 21200 | AS44: =Z44*AL44 -> 0 | AT44: =SUM(AM44:AS44) -> 106000 | AU44: =AB44*AL44 -> 21200 | AV44: =AC44*AL44 -> 21200 | AW44: =AD44*AL44 -> 21200 | AX44: =AE44*AL44 -> 21200 | AY44: =AF44*AL44 -> 21200 | AZ44: =AG44*AL44 -> 0 | BA44: =SUM(AU44:AZ44) -> 106000
A45: 32 | B45: DALI调光控制模块 | U45: 6 | V45: 6 | W45: 6 | X45: 6 | Y45: 6 | AA45: =SUM(T45:Z45) -> 30 | AB45: 6 | AC45: 6 | AD45: 6 | AE45: 6 | AF45: 6 | AH45: =SUM(AB45:AG45) -> 30 | AI45: nos | AK45: 9900 | AL45: =AJ45+AK45 -> 9900 | AM45: =T45*AL45 -> 0 | AN45: =U45*AL45 -> 59400 | AO45: =V45*AL45 -> 59400 | AP45: =W45*AL45 -> 59400 | AQ45: =X45*AL45 -> 59400 | AR45: =Y45*AL45 -> 59400 | AS45: =Z45*AL45 -> 0 | AT45: =SUM(AM45:AS45) -> 297000 | AU45: =AB45*AL45 -> 59400 | AV45: =AC45*AL45 -> 59400 | AW45: =AD45*AL45 -> 59400 | AX45: =AE45*AL45 -> 59400 | AY45: =AF45*AL45 -> 59400 | AZ45: =AG45*AL45 -> 0 | BA45: =SUM(AU45:AZ45) -> 297000
A46: 33 | B46: 8路开关控制模块 | U46: 1 | V46: 1 | W46: 1 | X46: 1 | Y46: 1 | AA46: =SUM(T46:Z46) -> 5 | AB46: 1 | AC46: 1 | AD46: 1 | AE46: 1 | AF46: 1 | AH46: =SUM(AB46:AG46) -> 5 | AI46: nos | AK46: 3510 | AL46: =AJ46+AK46 -> 3510 | AM46: =T46*AL46 -> 0 | AN46: =U46*AL46 -> 3510 | AO46: =V46*AL46 -> 3510 | AP46: =W46*AL46 -> 3510 | AQ46: =X46*AL46 -> 3510 | AR46: =Y46*AL46 -> 3510 | AS46: =Z46*AL46 -> 0 | AT46: =SUM(AM46:AS46) -> 17550 | AU46: =AB46*AL46 -> 3510 | AV46: =AC46*AL46 -> 3510 | AW46: =AD46*AL46 -> 3510 | AX46: =AE46*AL46 -> 3510 | AY46: =AF46*AL46 -> 3510 | AZ46: =AG46*AL46 -> 0 | BA46: =SUM(AU46:AZ46) -> 17550
A47: 34 | B47: 360º占空&日光感应器 | U47: 160 | V47: 158 | W47: 157 | X47: 155 | Y47: 142 | AA47: =SUM(T47:Z47) -> 772 | AB47: 158 | AC47: 156 | AD47: 162 | AE47: 159 | AF47: 143 | AH47: =SUM(AB47:AG47) -> 778 | AI47: nos | AK47: 1350 | AL47: =AJ47+AK47 -> 1350 | AM47: =T47*AL47 -> 0 | AN47: =U47*AL47 -> 216000 | AO47: =V47*AL47 -> 213300 | AP47: =W47*AL47 -> 211950 | AQ47: =X47*AL47 -> 209250 | AR47: =Y47*AL47 -> 191700 | AS47: =Z47*AL47 -> 0 | AT47: =SUM(AM47:AS47) -> 1042200 | AU47: =AB47*AL47 -> 213300 | AV47: =AC47*AL47 -> 210600 | AW47: =AD47*AL47 -> 218700 | AX47: =AE47*AL47 -> 214650 | AY47: =AF47*AL47 -> 193050 | AZ47: =AG47*AL47 -> 0 | BA47: =SUM(AU47:AZ47) -> 1050300
A48: 35 | B48: 智能控制面板 | U48: 37 | V48: 40 | W48: 45 | X48: 41 | Y48: 43 | AA48: =SUM(T48:Z48) -> 206 | AB48: 48 | AC48: 56 | AD48: 59 | AE48: 59 | AF48: 42 | AH48: =SUM(AB48:AG48) -> 264 | AI48: nos | AK48: 1250 | AL48: =AJ48+AK48 -> 1250 | AM48: =T48*AL48 -> 0 | AN48: =U48*AL48 -> 46250 | AO48: =V48*AL48 -> 50000 | AP48: =W48*AL48 -> 56250 | AQ48: =X48*AL48 -> 51250 | AR48: =Y48*AL48 -> 53750 | AS48: =Z48*AL48 -> 0 | AT48: =SUM(AM48:AS48) -> 257500 | AU48: =AB48*AL48 -> 60000 | AV48: =AC48*AL48 -> 70000 | AW48: =AD48*AL48 -> 73750 | AX48: =AE48*AL48 -> 73750 | AY48: =AF48*AL48 -> 52500 | AZ48: =AG48*AL48 -> 0 | BA48: =SUM(AU48:AZ48) -> 330000
A49: 36 | B49: BMS接口模块 | U49: 1 | AA49: =SUM(T49:Z49) -> 1 | AH49: =SUM(AB49:AG49) -> 0 | AI49: nos | AK49: 15400 | AL49: =AJ49+AK49 -> 15400 | AM49: =T49*AL49 -> 0 | AN49: =U49*AL49 -> 15400 | AO49: =V49*AL49 -> 0 | AP49: =W49*AL49 -> 0 | AQ49: =X49*AL49 -> 0 | AR49: =Y49*AL49 -> 0 | AS49: =Z49*AL49 -> 0 | AT49: =SUM(AM49:AS49) -> 15400 | AU49: =AB49*AL49 -> 0 | AV49: =AC49*AL49 -> 0 | AW49: =AD49*AL49 -> 0 | AX49: =AE49*AL49 -> 0 | AY49: =AF49*AL49 -> 0 | AZ49: =AG49*AL49 -> 0 | BA49: =SUM(AU49:AZ49) -> 0
A50: 37 | B50: 交换机 | U50: 1 | AA50: =SUM(T50:Z50) -> 1 | AB50: 1 | AH50: =SUM(AB50:AG50) -> 1 | AI50: nos | AK50: 1890 | AL50: =AJ50+AK50 -> 1890 | AM50: =T50*AL50 -> 0 | AN50: =U50*AL50 -> 1890 | AO50: =V50*AL50 -> 0 | AP50: =W50*AL50 -> 0 | AQ50: =X50*AL50 -> 0 | AR50: =Y50*AL50 -> 0 | AS50: =Z50*AL50 -> 0 | AT50: =SUM(AM50:AS50) -> 1890 | AU50: =AB50*AL50 -> 1890 | AV50: =AC50*AL50 -> 0 | AW50: =AD50*AL50 -> 0 | AX50: =AE50*AL50 -> 0 | AY50: =AF50*AL50 -> 0 | AZ50: =AG50*AL50 -> 0 | BA50: =SUM(AU50:AZ50) -> 1890
A51: 38 | B51: 照明系统中控软件 | U51: 1 | AA51: =SUM(T51:Z51) -> 1 | AH51: =SUM(AB51:AG51) -> 0 | AI51: nos | AK51: 45000 | AL51: =AJ51+AK51 -> 45000 | AM51: =T51*AL51 -> 0 | AN51: =U51*AL51 -> 45000 | AO51: =V51*AL51 -> 0 | AP51: =W51*AL51 -> 0 | AQ51: =X51*AL51 -> 0 | AR51: =Y51*AL51 -> 0 | AS51: =Z51*AL51 -> 0 | AT51: =SUM(AM51:AS51) -> 45000 | AU51: =AB51*AL51 -> 0 | AV51: =AC51*AL51 -> 0 | AW51: =AD51*AL51 -> 0 | AX51: =AE51*AL51 -> 0 | AY51: =AF51*AL51 -> 0 | AZ51: =AG51*AL51 -> 0 | BA51: =SUM(AU51:AZ51) -> 0
A52: 39 | B52: 中控电脑 | U52: 1 | AA52: =SUM(T52:Z52) -> 1 | AH52: =SUM(AB52:AG52) -> 0 | AI52: nos | AK52: 13000 | AL52: =AJ52+AK52 -> 13000 | AM52: =T52*AL52 -> 0 | AN52: =U52*AL52 -> 13000 | AO52: =V52*AL52 -> 0 | AP52: =W52*AL52 -> 0 | AQ52: =X52*AL52 -> 0 | AR52: =Y52*AL52 -> 0 | AS52: =Z52*AL52 -> 0 | AT52: =SUM(AM52:AS52) -> 13000 | AU52: =AB52*AL52 -> 0 | AV52: =AC52*AL52 -> 0 | AW52: =AD52*AL52 -> 0 | AX52: =AE52*AL52 -> 0 | AY52: =AF52*AL52 -> 0 | AZ52: =AG52*AL52 -> 0 | BA52: =SUM(AU52:AZ52) -> 0
A53: 40 | B53: 灯控系统系统通讯线 | U53: 1500 | V53: 1500 | W53: 1500 | X53: 1500 | Y53: 1500 | AA53: =SUM(T53:Z53) -> 7500 | AB53: 1650 | AC53: 1650 | AD53: 1650 | AE53: 1650 | AF53: 1500 | AH53: =SUM(AB53:AG53) -> 8100 | AI53: nos | AJ53: 6 | AK53: 6 | AL53: =AJ53+AK53 -> 12 | AM53: =T53*AL53 -> 0 | AN53: =U53*AL53 -> 18000 | AO53: =V53*AL53 -> 18000 | AP53: =W53*AL53 -> 18000 | AQ53: =X53*AL53 -> 18000 | AR53: =Y53*AL53 -> 18000 | AS53: =Z53*AL53 -> 0 | AT53: =SUM(AM53:AS53) -> 90000 | AU53: =AB53*AL53 -> 19800 | AV53: =AC53*AL53 -> 19800 | AW53: =AD53*AL53 -> 19800 | AX53: =AE53*AL53 -> 19800 | AY53: =AF53*AL53 -> 18000 | AZ53: =AG53*AL53 -> 0 | BA53: =SUM(AU53:AZ53) -> 97200
A54: 41 | B54: 系统编程调试测试（含中控编辑、界面制作、测试） | U54: 1 | V54: 1 | W54: 1 | X54: 1 | Y54: 1 | AA54: =SUM(T54:Z54) -> 5 | AB54: 1 | AC54: 1 | AD54: 1 | AE54: 1 | AF54: 1 | AH54: =SUM(AB54:AG54) -> 5 | AI54: item | AJ54: 65000 | AK54: 0 | AL54: =AJ54+AK54 -> 65000 | AM54: =T54*AL54 -> 0 | AN54: =U54*AL54 -> 65000 | AO54: =V54*AL54 -> 65000 | AP54: =W54*AL54 -> 65000 | AQ54: =X54*AL54 -> 65000 | AR54: =Y54*AL54 -> 65000 | AS54: =Z54*AL54 -> 0 | AT54: =SUM(AM54:AS54) -> 325000 | AU54: =AB54*AL54 -> 65000 | AV54: =AC54*AL54 -> 65000 | AW54: =AD54*AL54 -> 65000 | AX54: =AE54*AL54 -> 65000 | AY54: =AF54*AL54 -> 65000 | AZ54: =AG54*AL54 -> 0 | BA54: =SUM(AU54:AZ54) -> 325000
A55: 42 | AA55: =SUM(T55:Z55) -> 0 | AH55: =SUM(AB55:AG55) -> 0 | AL55: =AJ55+AK55 -> 0 | AM55: =T55*AL55 -> 0 | AN55: =U55*AL55 -> 0 | AO55: =V55*AL55 -> 0 | AP55: =W55*AL55 -> 0 | AQ55: =X55*AL55 -> 0 | AR55: =Y55*AL55 -> 0 | AS55: =Z55*AL55 -> 0 | AT55: =SUM(AM55:AS55) -> 0 | AU55: =AB55*AL55 -> 0 | AV55: =AC55*AL55 -> 0 | AW55: =AD55*AL55 -> 0 | AX55: =AE55*AL55 -> 0 | AY55: =AF55*AL55 -> 0 | AZ55: =AG55*AL55 -> 0 | BA55: =SUM(AU55:AZ55) -> 0
A56: 43 | B56: 电缆井及油管井开挖及复位 | U56: 1 | AA56: =SUM(T56:Z56) -> 1 | AH56: =SUM(AB56:AG56) -> 0 | AI56: item | AJ56: 42000 | AK56: 8000 | AL56: =AJ56+AK56 -> 50000 | AM56: =T56*AL56 -> 0 | AN56: =U56*AL56 -> 50000 | AO56: =V56*AL56 -> 0 | AP56: =W56*AL56 -> 0 | AQ56: =X56*AL56 -> 0 | AR56: =Y56*AL56 -> 0 | AS56: =Z56*AL56 -> 0 | AT56: =SUM(AM56:AS56) -> 50000 | AU56: =AB56*AL56 -> 0 | AV56: =AC56*AL56 -> 0 | AW56: =AD56*AL56 -> 0 | AX56: =AE56*AL56 -> 0 | AY56: =AF56*AL56 -> 0 | AZ56: =AG56*AL56 -> 0 | BA56: =SUM(AU56:AZ56) -> 0
A57: 44 | B57: 原有柴发油管拆除 | U57: 1 | AA57: =SUM(T57:Z57) -> 1 | AH57: =SUM(AB57:AG57) -> 0 | AI57: item | AJ57: 40000 | AL57: =AJ57+AK57 -> 40000 | AM57: =T57*AL57 -> 0 | AN57: =U57*AL57 -> 40000 | AO57: =V57*AL57 -> 0 | AP57: =W57*AL57 -> 0 | AQ57: =X57*AL57 -> 0 | AR57: =Y57*AL57 -> 0 | AS57: =Z57*AL57 -> 0 | AT57: =SUM(AM57:AS57) -> 40000 | AU57: =AB57*AL57 -> 0 | AV57: =AC57*AL57 -> 0 | AW57: =AD57*AL57 -> 0 | AX57: =AE57*AL57 -> 0 | AY57: =AF57*AL57 -> 0 | AZ57: =AG57*AL57 -> 0 | BA57: =SUM(AU57:AZ57) -> 0
B58: Sub-total | AM58: =SUBTOTAL(9,AM13:AM57) -> 0 | AN58: =SUBTOTAL(9,AN13:AN57) -> 866250 | AO58: =SUBTOTAL(9,AO13:AO57) -> 646385 | AP58: =SUBTOTAL(9,AP13:AP57) -> 688665 | AQ58: =SUBTOTAL(9,AQ13:AQ57) -> 646845 | AR58: =SUBTOTAL(9,AR13:AR57) -> 634025 | AS58: =SUBTOTAL(9,AS13:AS57) -> 1774542.8 | AT58: =SUBTOTAL(9,AT13:AT57) -> 5256712.8 | ... BA58: =SUBTOTAL(9,BA13:BA57) -> 3350455
A60: M | B60: Air-conditioning Works 空调工程（续）
A61: 45 | B61: 移位安装FTU风口，含故障排查及全面清洁 | L61: =SUM(F61:K61) -> 0 | S61: =SUM(M61:R61) -> 0 | T61: 0 | U61: 140 | V61: 99 | W61: 114 | X61: 98 | Y61: 100 | Z61: 0 | AA61: =SUM(T61:Z61) -> 551 | AB61: 79 | AC61: 92 | AD61: 90 | AE61: 92 | AF61: 84 | AG61: 0 | AH61: =SUM(AB61:AG61) -> 437 | AI61: nos | AJ61: 300 | AK61: 0 | AL61: =AJ61+AK61 -> 300 | AM61: =T61*AL61 -> 0 | AN61: =U61*AL61 -> 42000 | AO61: =V61*AL61 -> 29700 | AP61: =W61*AL61 -> 34200 | AQ61: =X61*AL61 -> 29400 | AR61: =Y61*AL61 -> 30000 | AS61: =Z61*AL61 -> 0 | AT61: =SUM(AM61:AS61) -> 165300 | AU61: =AB61*AL61 -> 23700 | AV61: =AC61*AL61 -> 27600 | AW61: =AD61*AL61 -> 27000 | AX61: =AE61*AL61 -> 27600 | AY61: =AF61*AL61 -> 25200 | AZ61: =AG61*AL61 -> 0 | BA61: =SUM(AU61:AZ61) -> 131100
A62: 46 | B62: FTU地板送风空调系统调试 -所有末端FTU分区及编号的设定 -指导安装末端FTU、FCP控制箱寄系统数据线连接工作 | L62: =SUM(F62:K62) -> 0 | S62: =SUM(M62:R62) -> 0 | T62: 0 | U62: 5 | V62: 5 | W62: 5 | X62: 5 | Y62: 5 | Z62: 0 | AA62: =SUM(T62:Z62) -> 25 | AB62: 5 | AC62: 5 | AD62: 5 | AE62: 5 | AF62: 5 | AG62: 0 | AH62: =SUM(AB62:AG62) -> 25 | AI62: nos | AJ62: 6250 | AK62: 0 | AL62: =AJ62+AK62 -> 6250 | AM62: =T62*AL62 -> 0 | AN62: =U62*AL62 -> 31250 | AO62: =V62*AL62 -> 31250 | AP62: =W62*AL62 -> 31250 | AQ62: =X62*AL62 -> 31250 | AR62: =Y62*AL62 -> 31250 | AS62: =Z62*AL62 -> 0 | AT62: =SUM(AM62:AS62) -> 156250 | AU62: =AB62*AL62 -> 31250 | AV62: =AC62*AL62 -> 31250 | AW62: =AD62*AL62 -> 31250 | AX62: =AE62*AL62 -> 31250 | AY62: =AF62*AL62 -> 31250 | AZ62: =AG62*AL62 -> 0 | BA62: =SUM(AU62:AZ62) -> 156250
A63: 47 | B63: 供应及安装静压箱1100*400*250（H） | L63: =SUM(F63:K63) -> 0 | S63: =SUM(M63:R63) -> 0 | T63: 0 | U63: 62 | V63: 53 | W63: 80 | X63: 62 | Y63: 79 | Z63: 0 | AA63: =SUM(T63:Z63) -> 336 | AB63: 52 | AC63: 54 | AD63: 60 | AE63: 57 | AF63: 60 | AG63: 0 | AH63: =SUM(AB63:AG63) -> 283 | AI63: set | AJ63: 75 | AK63: 285 | AL63: =AJ63+AK63 -> 360 | AM63: =T63*AL63 -> 0 | AN63: =U63*AL63 -> 22320 | AO63: =V63*AL63 -> 19080 | AP63: =W63*AL63 -> 28800 | AQ63: =X63*AL63 -> 22320 | AR63: =Y63*AL63 -> 28440 | AS63: =Z63*AL63 -> 0 | AT63: =SUM(AM63:AS63) -> 120960 | AU63: =AB63*AL63 -> 18720 | AV63: =AC63*AL63 -> 19440 | AW63: =AD63*AL63 -> 21600 | AX63: =AE63*AL63 -> 20520 | AY63: =AF63*AL63 -> 21600 | AZ63: =AG63*AL63 -> 0 | BA63: =SUM(AU63:AZ63) -> 101880
A64: 48 | B64: 供应及安装静压箱1100X1100X600（H） | L64: =SUM(F64:K64) -> 0 | S64: =SUM(M64:R64) -> 0 | T64: 0 | U64: 1 | V64: 0 | W64: 0 | X64: 0 | Y64: 0 | Z64: 0 | AA64: =SUM(T64:Z64) -> 1 | AB64: 0 | AC64: 4 | AD64: 4 | AE64: 4 | AF64: 0 | AG64: 0 | AH64: =SUM(AB64:AG64) -> 12 | AI64: set | AJ64: 100 | AK64: 892.5 | AL64: =AJ64+AK64 -> 992.5 | AM64: =T64*AL64 -> 0 | AN64: =U64*AL64 -> 992.5 | AO64: =V64*AL64 -> 0 | AP64: =W64*AL64 -> 0 | AQ64: =X64*AL64 -> 0 | AR64: =Y64*AL64 -> 0 | AS64: =Z64*AL64 -> 0 | AT64: =SUM(AM64:AS64) -> 992.5 | AU64: =AB64*AL64 -> 0 | AV64: =AC64*AL64 -> 3970 | AW64: =AD64*AL64 -> 3970 | AX64: =AE64*AL64 -> 3970 | AY64: =AF64*AL64 -> 0 | AZ64: =AG64*AL64 -> 0 | BA64: =SUM(AU64:AZ64) -> 11910
A65: 49 | B65: 供应及安装静压箱300*250*250（H） | L65: =SUM(F65:K65) -> 0 | S65: =SUM(M65:R65) -> 0 | T65: 0 | U65: 12 | V65: 18 | W65: 23 | X65: 17 | Y65: 18 | Z65: 0 | AA65: =SUM(T65:Z65) -> 88 | AB65: 22 | AC65: 31 | AD65: 33 | AE65: 35 | AF65: 17 | AG65: 0 | AH65: =SUM(AB65:AG65) -> 138 | AI65: set | AJ65: 37.5 | AK65: 135 | AL65: =AJ65+AK65 -> 172.5 | AM65: =T65*AL65 -> 0 | AN65: =U65*AL65 -> 2070 | AO65: =V65*AL65 -> 3105 | AP65: =W65*AL65 -> 3967.5 | AQ65: =X65*AL65 -> 2932.5 | AR65: =Y65*AL65 -> 3105 | AS65: =Z65*AL65 -> 0 | AT65: =SUM(AM65:AS65) -> 15180 | AU65: =AB65*AL65 -> 3795 | AV65: =AC65*AL65 -> 5347.5 | AW65: =AD65*AL65 -> 5692.5 | AX65: =AE65*AL65 -> 6037.5 | AY65: =AF65*AL65 -> 2932.5 | AZ65: =AG65*AL65 -> 0 | BA65: =SUM(AU65:AZ65) -> 23805
A66: 50 | B66: 供应及安装静压箱600*250*250（H） | L66: =SUM(F66:K66) -> 0 | S66: =SUM(M66:R66) -> 0 | T66: 0 | U66: 7 | V66: 20 | W66: 13 | X66: 15 | Y66: 13 | Z66: 0 | AA66: =SUM(T66:Z66) -> 68 | AB66: 11 | AC66: 9 | AD66: 8 | AE66: 6 | AF66: 8 | AG66: 0 | AH66: =SUM(AB66:AG66) -> 42 | AI66: set | AJ66: 62.5 | AK66: 210 | AL66: =AJ66+AK66 -> 272.5 | AM66: =T66*AL66 -> 0 | AN66: =U66*AL66 -> 1907.5 | AO66: =V66*AL66 -> 5450 | AP66: =W66*AL66 -> 3542.5 | AQ66: =X66*AL66 -> 4087.5 | AR66: =Y66*AL66 -> 3542.5 | AS66: =Z66*AL66 -> 0 | AT66: =SUM(AM66:AS66) -> 18530 | AU66: =AB66*AL66 -> 2997.5 | AV66: =AC66*AL66 -> 2452.5 | AW66: =AD66*AL66 -> 2180 | AX66: =AE66*AL66 -> 1635 | AY66: =AF66*AL66 -> 2180 | AZ66: =AG66*AL66 -> 0 | BA66: =SUM(AU66:AZ66) -> 11445
A67: 51 | B67: 供应及安装隔音毡 | L67: =SUM(F67:K67) -> 0 | S67: =SUM(M67:R67) -> 0 | T67: 0 | U67: 11.661 | V67: 11.661 | W67: 11.661 | X67: 11.661 | Y67: 0 | Z67: 0 | AA67: =SUM(T67:Z67) -> 46.644 | AB67: 11.178 | AC67: 15.07788 | AD67: 15.07788 | AE67: 33.59288 | AF67: 11.178 | AG67: 0 | AH67: =SUM(AB67:AG67) -> 86.10464 | AI67: ㎡ | AJ67: 81.25 | AK67: 37.5 | AL67: =AJ67+AK67 -> 118.75 | AM67: =T67*AL67 -> 0 | AN67: =U67*AL67 -> 1384.7437 | AO67: =V67*AL67 -> 1384.7437 | AP67: =W67*AL67 -> 1384.7437 | AQ67: =X67*AL67 -> 1384.7437 | AR67: =Y67*AL67 -> 0 | AS67: =Z67*AL67 -> 0 | AT67: =SUM(AM67:AS67) -> 5538.975 | AU67: =AB67*AL67 -> 1327.3875 | AV67: =AC67*AL67 -> 1790.4982 | AW67: =AD67*AL67 -> 1790.4982 | AX67: =AE67*AL67 -> 3989.1545 | AY67: =AF67*AL67 -> 1327.3875 | AZ67: =AG67*AL67 -> 0 | BA67: =SUM(AU67:AZ67) -> 10224.926
A68: 52 | B68: 供应及安装AH单层格栅风口1250*（150-300） | D68: 显隆 | L68: =SUM(F68:K68) -> 0 | S68: =SUM(M68:R68) -> 0 | T68: 0 | U68: 5 | V68: 2 | W68: 6 | X68: 6 | Y68: 6 | Z68: 0 | AA68: =SUM(T68:Z68) -> 25 | AB68: 4 | AC68: 1 | AD68: 2 | AE68: 4 | AF68: 2 | AG68: 0 | AH68: =SUM(AB68:AG68) -> 13 | AI68: nos | AJ68: 150 | AK68: 420 | AL68: =AJ68+AK68 -> 570 | AM68: =T68*AL68 -> 0 | AN68: =U68*AL68 -> 2850 | AO68: =V68*AL68 -> 1140 | AP68: =W68*AL68 -> 3420 | AQ68: =X68*AL68 -> 3420 | AR68: =Y68*AL68 -> 3420 | AS68: =Z68*AL68 -> 0 | AT68: =SUM(AM68:AS68) -> 14250 | AU68: =AB68*AL68 -> 2280 | AV68: =AC68*AL68 -> 570 | AW68: =AD68*AL68 -> 1140 | AX68: =AE68*AL68 -> 2280 | AY68: =AF68*AL68 -> 1140 | AZ68: =AG68*AL68 -> 0 | BA68: =SUM(AU68:AZ68) -> 7410
A69: 53 | B69: 供应及安装AH单层格栅风口2000*200 | D69: 显隆 | L69: =SUM(F69:K69) -> 0 | S69: =SUM(M69:R69) -> 0 | T69: 0 | U69: 0 | V69: 2 | W69: 0 | X69: 1 | Y69: 1 | Z69: 0 | AA69: =SUM(T69:Z69) -> 4 | AB69: 0 | AC69: 0 | AD69: 0 | AE69: 0 | AF69: 0 | AG69: 0 | AH69: =SUM(AB69:AG69) -> 0 | AI69: nos | AJ69: 200 | AK69: 540 | AL69: =AJ69+AK69 -> 740 | AM69: =T69*AL69 -> 0 | AN69: =U69*AL69 -> 0 | AO69: =V69*AL69 -> 1480 | AP69: =W69*AL69 -> 0 | AQ69: =X69*AL69 -> 740 | AR69: =Y69*AL69 -> 740 | AS69: =Z69*AL69 -> 0 | AT69: =SUM(AM69:AS69) -> 2960 | AU69: =AB69*AL69 -> 0 | AV69: =AC69*AL69 -> 0 | AW69: =AD69*AL69 -> 0 | AX69: =AE69*AL69 -> 0 | AY69: =AF69*AL69 -> 0 | AZ69: =AG69*AL69 -> 0 | BA69: =SUM(AU69:AZ69) -> 0
A70: 54 | B70: 供应及安装AH单层格栅风口600*150 | D70: 显隆 | L70: =SUM(F70:K70) -> 0 | S70: =SUM(M70:R70) -> 0 | T70: 0 | U70: 0 | V70: 3 | W70: 0 | X70: 3 | Y70: 1 | Z70: 0 | AA70: =SUM(T70:Z70) -> 7 | AB70: 0 | AC70: 0 | AD70: 0 | AE70: 0 | AF70: 0 | AG70: 0 | AH70: =SUM(AB70:AG70) -> 0 | AI70: nos | AJ70: 62.5 | AK70: 164 | AL70: =AJ70+AK70 -> 226.5 | AM70: =T70*AL70 -> 0 | AN70: =U70*AL70 -> 0 | AO70: =V70*AL70 -> 679.5 | AP70: =W70*AL70 -> 0 | AQ70: =X70*AL70 -> 679.5 | AR70: =Y70*AL70 -> 226.5 | AS70: =Z70*AL70 -> 0 | AT70: =SUM(AM70:AS70) -> 1585.5 | AU70: =AB70*AL70 -> 0 | AV70: =AC70*AL70 -> 0 | AW70: =AD70*AL70 -> 0 | AX70: =AE70*AL70 -> 0 | AY70: =AF70*AL70 -> 0 | AZ70: =AG70*AL70 -> 0 | BA70: =SUM(AU70:AZ70) -> 0
A71: 55 | B71: 供应及安装AH单层格栅风口800*（150-300） | D71: 显隆 | L71: =SUM(F71:K71) -> 0 | S71: =SUM(M71:R71) -> 0 | T71: 0 | U71: 14 | V71: 14 | W71: 13 | X71: 10 | Y71: 15 | Z71: 0 | AA71: =SUM(T71:Z71) -> 66 | AB71: 17 | AC71: 24 | AD71: 24 | AE71: 23 | AF71: 20 | AG71: 0 | AH71: =SUM(AB71:AG71) -> 108 | AI71: nos | AJ71: 68.75 | AK71: 325 | AL71: =AJ71+AK71 -> 393.75 | AM71: =T71*AL71 -> 0 | AN71: =U71*AL71 -> 5512.5 | AO71: =V71*AL71 -> 5512.5 | AP71: =W71*AL71 -> 5118.75 | AQ71: =X71*AL71 -> 3937.5 | AR71: =Y71*AL71 -> 5906.25 | AS71: =Z71*AL71 -> 0 | AT71: =SUM(AM71:AS71) -> 25987.5 | AU71: =AB71*AL71 -> 6693.75 | AV71: =AC71*AL71 -> 9450 | AW71: =AD71*AL71 -> 9450 | AX71: =AE71*AL71 -> 9056.25 | AY71: =AF71*AL71 -> 7875 | AZ71: =AG71*AL71 -> 0 | BA71: =SUM(AU71:AZ71) -> 42525
A72: 56 | B72: 供应及安装AH单层格栅风口1600*200 | D72: 显隆 | L72: =SUM(F72:K72) -> 0 | S72: =SUM(M72:R72) -> 0 | T72: 0 | U72: 0 | V72: 0 | W72: 0 | X72: 0 | Y72: 0 | Z72: 0 | AA72: =SUM(T72:Z72) -> 0 | AB72: 1 | AC72: 0 | AD72: 2 | AE72: 0 | AF72: 0 | AG72: 0 | AH72: =SUM(AB72:AG72) -> 3 | AI72: nos | AJ72: 162.5 | AK72: 468 | AL72: =AJ72+AK72 -> 630.5 | AM72: =T72*AL72 -> 0 | AN72: =U72*AL72 -> 0 | AO72: =V72*AL72 -> 0 | AP72: =W72*AL72 -> 0 | AQ72: =X72*AL72 -> 0 | AR72: =Y72*AL72 -> 0 | AS72: =Z72*AL72 -> 0 | AT72: =SUM(AM72:AS72) -> 0 | AU72: =AB72*AL72 -> 630.5 | AV72: =AC72*AL72 -> 0 | AW72: =AD72*AL72 -> 1261 | AX72: =AE72*AL72 -> 0 | AY72: =AF72*AL72 -> 0 | AZ72: =AG72*AL72 -> 0 | BA72: =SUM(AU72:AZ72) -> 1891.5
A73: 57 | B73: 供应及安装AH单层格栅风口1000*200 | D73: 显隆 | L73: =SUM(F73:K73) -> 0 | S73: =SUM(M73:R73) -> 0 | T73: 0 | U73: 0 | V73: 0 | W73: 0 | X73: 0 | Y73: 0 | Z73: 0 | AA73: =SUM(T73:Z73) -> 0 | AB73: 0 | AC73: 0 | AD73: 0 | AE73: 0 | AF73: 1 | AG73: 0 | AH73: =SUM(AB73:AG73) -> 1 | AI73: nos | AJ73: 100 | AK73: 320 | AL73: =AJ73+AK73 -> 420 | AM73: =T73*AL73 -> 0 | AN73: =U73*AL73 -> 0 | AO73: =V73*AL73 -> 0 | AP73: =W73*AL73 -> 0 | AQ73: =X73*AL73 -> 0 | AR73: =Y73*AL73 -> 0 | AS73: =Z73*AL73 -> 0 | AT73: =SUM(AM73:AS73) -> 0 | AU73: =AB73*AL73 -> 0 | AV73: =AC73*AL73 -> 0 | AW73: =AD73*AL73 -> 0 | AX73: =AE73*AL73 -> 0 | AY73: =AF73*AL73 -> 420 | AZ73: =AG73*AL73 -> 0 | BA73: =SUM(AU73:AZ73) -> 420
A74: 58 | B74: 供应及安装地面条形风口250mm宽 | D74: 显隆 | L74: =SUM(F74:K74) -> 0 | S74: =SUM(M74:R74) -> 0 | T74: 0 | U74: 242 | V74: 311 | W74: 374 | X74: 343 | Y74: 344 | Z74: 0 | AA74: =SUM(T74:Z74) -> 1614 | AB74: 320.87875 | AC74: 354.4415 | AD74: 402.4655 | AE74: 367.63315 | AF74: 328.88275 | AG74: 0 | AH74: =SUM(AB74:AG74) -> 1774.3016 | AI74: m | AJ74: 100 | AK74: 625 | AL74: =AJ74+AK74 -> 725 | AM74: =T74*AL74 -> 0 | AN74: =U74*AL74 -> 175450 | AO74: =V74*AL74 -> 225475 | AP74: =W74*AL74 -> 271150 | AQ74: =X74*AL74 -> 248675 | AR74: =Y74*AL74 -> 249400 | AS74: =Z74*AL74 -> 0 | AT74: =SUM(AM74:AS74) -> 1170150 | AU74: =AB74*AL74 -> 232637.09 | AV74: =AC74*AL74 -> 256970.09 | AW74: =AD74*AL74 -> 291787.49 | AX74: =AE74*AL74 -> 266534.03 | AY74: =AF74*AL74 -> 238439.99 | AZ74: =AG74*AL74 -> 0 | BA74: =SUM(AU74:AZ74) -> 1286368.7
A75: 59 | B75: 供应及安装天花条形风口150mm宽 | D75: 显隆 | L75: =SUM(F75:K75) -> 0 | S75: =SUM(M75:R75) -> 0 | T75: 0 | U75: 116 | V75: 76 | W75: 123 | X75: 115 | Y75: 94 | Z75: 0 | AA75: =SUM(T75:Z75) -> 524 | AB75: 118.772 | AC75: 137.20075 | AD75: 157.7685 | AE75: 132.5904 | AF75: 101.062 | AG75: 0 | AH75: =SUM(AB75:AG75) -> 647.39365 | AI75: m | AJ75: 68.75 | AK75: 250 | AL75: =AJ75+AK75 -> 318.75 | AM75: =T75*AL75 -> 0 | AN75: =U75*AL75 -> 36975 | AO75: =V75*AL75 -> 24225 | AP75: =W75*AL75 -> 39206.25 | AQ75: =X75*AL75 -> 36656.25 | AR75: =Y75*AL75 -> 29962.5 | AS75: =Z75*AL75 -> 0 | AT75: =SUM(AM75:AS75) -> 167025 | AU75: =AB75*AL75 -> 37858.575 | AV75: =AC75*AL75 -> 43732.739 | AW75: =AD75*AL75 -> 50288.709 | AX75: =AE75*AL75 -> 42263.19 | AY75: =AF75*AL75 -> 32213.512 | AZ75: =AG75*AL75 -> 0 | BA75: =SUM(AU75:AZ75) -> 206356.73
A76: 60 | B76: 供应及安装天花条形风口300mm宽 | D76: 显隆 | L76: =SUM(F76:K76) -> 0 | S76: =SUM(M76:R76) -> 0 | T76: 0 | U76: 11 | V76: 0 | W76: 0 | X76: 0 | Y76: 0 | Z76: 0 | AA76: =SUM(T76:Z76) -> 11 | AB76: 3.105 | AC76: 3.473 | AD76: 7.3255 | AE76: 3.473 | AF76: 3.5075 | AG76: 0 | AH76: =SUM(AB76:AG76) -> 20.884 | AI76: m | AJ76: 112.5 | AK76: 400 | AL76: =AJ76+AK76 -> 512.5 | AM76: =T76*AL76 -> 0 | AN76: =U76*AL76 -> 5637.5 | AO76: =V76*AL76 -> 0 | AP76: =W76*AL76 -> 0 | AQ76: =X76*AL76 -> 0 | AR76: =Y76*AL76 -> 0 | AS76: =Z76*AL76 -> 0 | AT76: =SUM(AM76:AS76) -> 5637.5 | AU76: =AB76*AL76 -> 1591.3125 | AV76: =AC76*AL76 -> 1779.9125 | AW76: =AD76*AL76 -> 3754.3187 | AX76: =AE76*AL76 -> 1779.9125 | AY76: =AF76*AL76 -> 1797.5937 | AZ76: =AG76*AL76 -> 0 | BA76: =SUM(AU76:AZ76) -> 10703.05
A77: 61 | B77: 供应及安装防火阀FDS 1000*300 | D77: 显隆 | L77: =SUM(F77:K77) -> 0 | S77: =SUM(M77:R77) -> 0 | T77: 0 | U77: 27 | V77: 23 | W77: 24 | X77: 22 | Y77: 20 | Z77: 0 | AA77: =SUM(T77:Z77) -> 116 | AB77: 24 | AC77: 23 | AD77: 24 | AE77: 25 | AF77: 19 | AG77: 0 | AH77: =SUM(AB77:AG77) -> 115 | AI77: nos | AJ77: 125 | AK77: 871.25 | AL77: =AJ77+AK77 -> 996.25 | AM77: =T77*AL77 -> 0 | AN77: =U77*AL77 -> 26898.75 | AO77: =V77*AL77 -> 22913.75 | AP77: =W77*AL77 -> 23910 | AQ77: =X77*AL77 -> 21917.5 | AR77: =Y77*AL77 -> 19925 | AS77: =Z77*AL77 -> 0 | AT77: =SUM(AM77:AS77) -> 115565 | AU77: =AB77*AL77 -> 23910 | AV77: =AC77*AL77 -> 22913.75 | AW77: =AD77*AL77 -> 23910 | AX77: =AE77*AL77 -> 24906.25 | AY77: =AF77*AL77 -> 18928.75 | AZ77: =AG77*AL77 -> 0 | BA77: =SUM(AU77:AZ77) -> 114568.75
A78: 62 | B78: 供应及安装防火阀FDS 500*300 | D78: 显隆 | L78: =SUM(F78:K78) -> 0 | S78: =SUM(M78:R78) -> 0 | T78: 0 | U78: 2 | V78: 2 | W78: 2 | X78: 1 | Y78: 1 | Z78: 0 | AA78: =SUM(T78:Z78) -> 8 | AB78: 0 | AC78: 0 | AD78: 0 | AE78: 0 | AF78: 0 | AG78: 0 | AH78: =SUM(AB78:AG78) -> 0 | AI78: nos | AJ78: 62.5 | AK78: 621.25 | AL78: =AJ78+AK78 -> 683.75 | AM78: =T78*AL78 -> 0 | AN78: =U78*AL78 -> 1367.5 | AO78: =V78*AL78 -> 1367.5 | AP78: =W78*AL78 -> 1367.5 | AQ78: =X78*AL78 -> 683.75 | AR78: =Y78*AL78 -> 683.75 | AS78: =Z78*AL78 -> 0 | AT78: =SUM(AM78:AS78) -> 5470 | AU78: =AB78*AL78 -> 0 | AV78: =AC78*AL78 -> 0 | AW78: =AD78*AL78 -> 0 | AX78: =AE78*AL78 -> 0 | AY78: =AF78*AL78 -> 0 | AZ78: =AG78*AL78 -> 0 | BA78: =SUM(AU78:AZ78) -> 0
A79: 63 | B79: 供应及安装多叶调节风阀 200*200 | D79: 显隆 | L79: =SUM(F79:K79) -> 0 | S79: =SUM(M79:R79) -> 0 | T79: 0 | U79: 3 | V79: 0 | W79: 0 | X79: 0 | Y79: 0 | Z79: 0 | AA79: =SUM(T79:Z79) -> 3 | AB79: 0 | AC79: 2 | AD79: 2 | AE79: 2 | AF79: 0 | AG79: 0 | AH79: =SUM(AB79:AG79) -> 6 | AI79: nos | AJ79: 43.75 | AK79: 150 | AL79: =AJ79+AK79 -> 193.75 | AM79: =T79*AL79 -> 0 | AN79: =U79*AL79 -> 581.25 | AO79: =V79*AL79 -> 0 | AP79: =W79*AL79 -> 0 | AQ79: =X79*AL79 -> 0 | AR79: =Y79*AL79 -> 0 | AS79: =Z79*AL79 -> 0 | AT79: =SUM(AM79:AS79) -> 581.25 | AU79: =AB79*AL79 -> 0 | AV79: =AC79*AL79 -> 387.5 | AW79: =AD79*AL79 -> 387.5 | AX79: =AE79*AL79 -> 387.5 | AY79: =AF79*AL79 -> 0 | AZ79: =AG79*AL79 -> 0 | BA79: =SUM(AU79:AZ79) -> 1162.5
... A90: 74 | B90: 供应及安装消声器1500*625*550（H） | D90: 华东正大 | L90: =SUM(F90:K90) -> 0 | S90: =SUM(M90:R90) -> 0 | T90: 0 | U90: 1 | V90: 0 | W90: 0 | X90: 0 | Y90: 0 | Z90: 0 | AA90: =SUM(T90:Z90) -> 1 | AB90: 0 | AC90: 0 | AD90: 1 | AE90: 2 | AF90: 1 | AG90: 0 | AH90: =SUM(AB90:AG90) -> 4 | AI90: nos | AJ90: 175 | AK90: 1790.367 | AL90: =AJ90+AK90 -> 1965.367 | AM90: =T90*AL90 -> 0 | AN90: =U90*AL90 -> 1965.367 | AO90: =V90*AL90 -> 0 | AP90: =W90*AL90 -> 0 | AQ90: =X90*AL90 -> 0 | AR90: =Y90*AL90 -> 0 | AS90: =Z90*AL90 -> 0 | AT90: =SUM(AM90:AS90) -> 1965.367 | AU90: =AB90*AL90 -> 0 | AV90: =AC90*AL90 -> 0 | AW90: =AD90*AL90 -> 1965.367 | AX90: =AE90*AL90 -> 3930.7339 | AY90: =AF90*AL90 -> 1965.367 | AZ90: =AG90*AL90 -> 0 | BA90: =SUM(AU90:AZ90) -> 7861.4679
A91: 75 | B91: 移位消声器1500*1250*550（H） | L91: =SUM(F91:K91) -> 0 | S91: =SUM(M91:R91) -> 0 | T91: 0 | U91: 6 | V91: 6 | W91: 8 | X91: 8 | Y91: 5 | Z91: 0 | AA91: =SUM(T91:Z91) -> 33 | AB91: 6 | AC91: 7 | AD91: 8 | AE91: 7 | AF91: 7 | AG91: 0 | AH91: =SUM(AB91:AG91) -> 35 | AI91: nos | AJ91: 275 | AK91: 0 | AL91: =AJ91+AK91 -> 275 | AM91: =T91*AL91 -> 0 | AN91: =U91*AL91 -> 1650 | AO91: =V91*AL91 -> 1650 | AP91: =W91*AL91 -> 2200 | AQ91: =X91*AL91 -> 2200 | AR91: =Y91*AL91 -> 1375 | AS91: =Z91*AL91 -> 0 | AT91: =SUM(AM91:AS91) -> 9075 | AU91: =AB91*AL91 -> 1650 | AV91: =AC91*AL91 -> 1925 | AW91: =AD91*AL91 -> 2200 | AX91: =AE91*AL91 -> 1925 | AY91: =AF91*AL91 -> 1925 | AZ91: =AG91*AL91 -> 0 | BA91: =SUM(AU91:AZ91) -> 9625
A92: 76 | B92: 移位消声器1500*625*550（H） | L92: =SUM(F92:K92) -> 0 | S92: =SUM(M92:R92) -> 0 | T92: 0 | U92: 0 | V92: 0 | W92: 0 | X92: 1 | Y92: 0 | Z92: 0 | AA92: =SUM(T92:Z92) -> 1 | AB92: 0 | AC92: 0 | AD92: 0 | AE92: 0 | AF92: 0 | AG92: 0 | AH92: =SUM(AB92:AG92) -> 0 | AI92: nos | AJ92: 275 | AK92: 0 | AL92: =AJ92+AK92 -> 275 | AM92: =T92*AL92 -> 0 | AN92: =U92*AL92 -> 0 | AO92: =V92*AL92 -> 0 | AP92: =W92*AL92 -> 0 | AQ92: =X92*AL92 -> 275 | AR92: =Y92*AL92 -> 0 | AS92: =Z92*AL92 -> 0 | AT92: =SUM(AM92:AS92) -> 275 | AU92: =AB92*AL92 -> 0 | AV92: =AC92*AL92 -> 0 | AW92: =AD92*AL92 -> 0 | AX92: =AE92*AL92 -> 0 | AY92: =AF92*AL92 -> 0 | AZ92: =AG92*AL92 -> 0 | BA92: =SUM(AU92:AZ92) -> 0
A93: 77 | B93: 供应及安装L型消声连通管1250*200 | L93: =SUM(F93:K93) -> 0 | S93: =SUM(M93:R93) -> 0 | T93: 0 | U93: 0 | V93: 4 | W93: 5 | X93: 5 | Y93: 5 | Z93: 0 | AA93: =SUM(T93:Z93) -> 19 | AB93: 1 | AC93: 1 | AD93: 1 | AE93: 1 | AF93: 1 | AG93: 1 | AH93: =SUM(AB93:AG93) -> 6 | AI93: nos | AJ93: 375 | AK93: 1500 | AL93: =AJ93+AK93 -> 1875 | AM93: =T93*AL93 -> 0 | AN93: =U93*AL93 -> 0 | AO93: =V93*AL93 -> 7500 | AP93: =W93*AL93 -> 9375 | AQ93: =X93*AL93 -> 9375 | AR93: =Y93*AL93 -> 9375 | AS93: =Z93*AL93 -> 0 | AT93: =SUM(AM93:AS93) -> 35625 | AU93: =AB93*AL93 -> 1875 | AV93: =AC93*AL93 -> 1875 | AW93: =AD93*AL93 -> 1875 | AX93: =AE93*AL93 -> 1875 | AY93: =AF93*AL93 -> 1875 | AZ93: =AG93*AL93 -> 1875 | BA93: =SUM(AU93:AZ93) -> 11250
A94: 78 | B94: 供应及安装L型消声连通管1000*200 | L94: =SUM(F94:K94) -> 0 | S94: =SUM(M94:R94) -> 0 | T94: 0 | U94: 0 | V94: 0 | W94: 0 | X94: 0 | Y94: 0 | Z94: 0 | AA94: =SUM(T94:Z94) -> 0 | AB94: 0 | AC94: 0 | AD94: 0 | AE94: 0 | AF94: 1 | AG94: 0 | AH94: =SUM(AB94:AG94) -> 1 | AI94: nos | AJ94: 375 | AK94: 1375 | AL94: =AJ94+AK94 -> 1750 | AM94: =T94*AL94 -> 0 | AN94: =U94*AL94 -> 0 | AO94: =V94*AL94 -> 0 | AP94: =W94*AL94 -> 0 | AQ94: =X94*AL94 -> 0 | AR94: =Y94*AL94 -> 0 | AS94: =Z94*AL94 -> 0 | AT94: =SUM(AM94:AS94) -> 0 | AU94: =AB94*AL94 -> 0 | AV94: =AC94*AL94 -> 0 | AW94: =AD94*AL94 -> 0 | AX94: =AE94*AL94 -> 0 | AY94: =AF94*AL94 -> 1750 | AZ94: =AG94*AL94 -> 0 | BA94: =SUM(AU94:AZ94) -> 1750
A95: 79 | B95: 供应及安装L型消声连通管1250*300 | L95: =SUM(F95:K95) -> 0 | S95: =SUM(M95:R95) -> 0 | T95: 0 | U95: 4 | V95: 0 | W95: 0 | X95: 0 | Y95: 0 | Z95: 0 | AA95: =SUM(T95:Z95) -> 4 | AB95: 0 | AC95: 0 | AD95: 0 | AE95: 0 | AF95: 0 | AG95: 0 | AH95: =SUM(AB95:AG95) -> 0 | AI95: nos | AJ95: 375 | AK95: 1500 | AL95: =AJ95+AK95 -> 1875 | AM95: =T95*AL95 -> 0 | AN95: =U95*AL95 -> 7500 | AO95: =V95*AL95 -> 0 | AP95: =W95*AL95 -> 0 | AQ95: =X95*AL95 -> 0 | AR95: =Y95*AL95 -> 0 | AS95: =Z95*AL95 -> 0 | AT95: =SUM(AM95:AS95) -> 7500 | AU95: =AB95*AL95 -> 0 | AV95: =AC95*AL95 -> 0 | AW95: =AD95*AL95 -> 0 | AX95: =AE95*AL95 -> 0 | AY95: =AF95*AL95 -> 0 | AZ95: =AG95*AL95 -> 0 | BA95: =SUM(AU95:AZ95) -> 0
A96: 80 | B96: 供应及安装L型消声连通管1600*200 | L96: =SUM(F96:K96) -> 0 | S96: =SUM(M96:R96) -> 0 | T96: 0 | U96: 0 | V96: 0 | W96: 0 | X96: 0 | Y96: 0 | Z96: 0 | AA96: =SUM(T96:Z96) -> 0 | AB96: 1 | AC96: 0 | AD96: 0 | AE96: 0 | AF96: 0 | AG96: 0 | AH96: =SUM(AB96:AG96) -> 1 | AI96: nos | AJ96: 475 | AK96: 1875 | AL96: =AJ96+AK96 -> 2350 | AM96: =T96*AL96 -> 0 | AN96: =U96*AL96 -> 0 | AO96: =V96*AL96 -> 0 | AP96: =W96*AL96 -> 0 | AQ96: =X96*AL96 -> 0 | AR96: =Y96*AL96 -> 0 | AS96: =Z96*AL96 -> 0 | AT96: =SUM(AM96:AS96) -> 0 | AU96: =AB96*AL96 -> 2350 | AV96: =AC96*AL96 -> 0 | AW96: =AD96*AL96 -> 0 | AX96: =AE96*AL96 -> 0 | AY96: =AF96*AL96 -> 0 | AZ96: =AG96*AL96 -> 0 | BA96: =SUM(AU96:AZ96) -> 2350
A97: 81 | B97: 供应及安装L型消声连通管800*150 | L97: =SUM(F97:K97) -> 0 | S97: =SUM(M97:R97) -> 0 | T97: 0 | U97: 2 | V97: 0 | W97: 0 | X97: 0 | Y97: 0 | Z97: 0 | AA97: =SUM(T97:Z97) -> 2 | AB97: 0 | AC97: 0 | AD97: 0 | AE97: 0 | AF97: 0 | AG97: 0 | AH97: =SUM(AB97:AG97) -> 0 | AI97: nos | AJ97: 87.5 | AK97: 375 | AL97: =AJ97+AK97 -> 462.5 | AM97: =T97*AL97 -> 0 | AN97: =U97*AL97 -> 925 | AO97: =V97*AL97 -> 0 | AP97: =W97*AL97 -> 0 | AQ97: =X97*AL97 -> 0 | AR97: =Y97*AL97 -> 0 | AS97: =Z97*AL97 -> 0 | AT97: =SUM(AM97:AS97) -> 925 | AU97: =AB97*AL97 -> 0 | AV97: =AC97*AL97 -> 0 | AW97: =AD97*AL97 -> 0 | AX97: =AE97*AL97 -> 0 | AY97: =AF97*AL97 -> 0 | AZ97: =AG97*AL97 -> 0 | BA97: =SUM(AU97:AZ97) -> 0
A98: 82 | B98: 供应及安装L型消声连通管800*200 | L98: =SUM(F98:K98) -> 0 | S98: =SUM(M98:R98) -> 0 | T98: 0 | U98: 0 | V98: 0 | W98: 0 | X98: 0 | Y98: 0 | Z98: 0 | AA98: =SUM(T98:Z98) -> 0 | AB98: 0 | AC98: 1 | AD98: 1 | AE98: 1 | AF98: 1 | AG98: 0 | AH98: =SUM(AB98:AG98) -> 4 | AI98: nos | AJ98: 87.5 | AK98: 437.5 | AL98: =AJ98+AK98 -> 525 | AM98: =T98*AL98 -> 0 | AN98: =U98*AL98 -> 0 | AO98: =V98*AL98 -> 0 | AP98: =W98*AL98 -> 0 | AQ98: =X98*AL98 -> 0 | AR98: =Y98*AL98 -> 0 | AS98: =Z98*AL98 -> 0 | AT98: =SUM(AM98:AS98) -> 0 | AU98: =AB98*AL98 -> 0 | AV98: =AC98*AL98 -> 525 | AW98: =AD98*AL98 -> 525 | AX98: =AE98*AL98 -> 525 | AY98: =AF98*AL98 -> 525 | AZ98: =AG98*AL98 -> 0 | BA98: =SUM(AU98:AZ98) -> 2100
A99: 83 | B99: 供应及安装Z型消声连通管1250*150 | L99: =SUM(F99:K99) -> 0 | S99: =SUM(M99:R99) -> 0 | T99: 0 | U99: 0 | V99: 0 | W99: 0 | X99: 0 | Y99: 1 | Z99: 0 | AA99: =SUM(T99:Z99) -> 1 | AB99: 1 | AC99: 0 | AD99: 1 | AE99: 0 | AF99: 0 | AG99: 0 | AH99: =SUM(AB99:AG99) -> 2 | AI99: nos | AJ99: 375 | AK99: 1437.5 | AL99: =AJ99+AK99 -> 1812.5 | AM99: =T99*AL99 -> 0 | AN99: =U99*AL99 -> 0 | AO99: =V99*AL99 -> 0 | AP99: =W99*AL99 -> 0 | AQ99: =X99*AL99 -> 0 | AR99: =Y99*AL99 -> 1812.5 | AS99: =Z99*AL99 -> 0 | AT99: =SUM(AM99:AS99) -> 1812.5 | AU99: =AB99*AL99 -> 1812.5 | AV99: =AC99*AL99 -> 0 | AW99: =AD99*AL99 -> 1812.5 | AX99: =AE99*AL99 -> 0 | AY99: =AF99*AL99 -> 0 | AZ99: =AG99*AL99 -> 0 | BA99: =SUM(AU99:AZ99) -> 3625
A100: 84 | B100: 供应及安装Z型消声连通管1250*200 | L100: =SUM(F100:K100) -> 0 | S100: =SUM(M100:R100) -> 0 | T100: 0 | U100: 1 | V100: 1 | W100: 1 | X100: 1 | Y100: 0 | Z100: 0 | AA100: =SUM(T100:Z100) -> 4 | AB100: 0 | AC100: 0 | AD100: 0 | AE100: 0 | AF100: 0 | AG100: 0 | AH100: =SUM(AB100:AG100) -> 0 | AI100: nos | AJ100: 375 | AK100: 1500 | AL100: =AJ100+AK100 -> 1875 | AM100: =T100*AL100 -> 0 | AN100: =U100*AL100 -> 1875 | AO100: =V100*AL100 -> 1875 | AP100: =W100*AL100 -> 1875 | AQ100: =X100*AL100 -> 1875 | AR100: =Y100*AL100 -> 0 | AS100: =Z100*AL100 -> 0 | AT100: =SUM(AM100:AS100) -> 7500 | AU100: =AB100*AL100 -> 0 | AV100: =AC100*AL100 -> 0 | AW100: =AD100*AL100 -> 0 | AX100: =AE100*AL100 -> 0 | AY100: =AF100*AL100 -> 0 | AZ100: =AG100*AL100 -> 0 | BA100: =SUM(AU100:AZ100) -> 0
A101: 85 | B101: 供应及安装Z型消声连通管1250*300 | L101: =SUM(F101:K101) -> 0 | S101: =SUM(M101:R101) -> 0 | T101: 0 | U101: 0 | V101: 0 | W101: 0 | X101: 0 | Y101: 0 | Z101: 0 | AA101: =SUM(T101:Z101) -> 0 | AB101: 3 | AC101: 0 | AD101: 0 | AE101: 0 | AF101: 0 | AG101: 0 | AH101: =SUM(AB101:AG101) -> 3 | AI101: nos | AJ101: 375 | AK101: 1625 | AL101: =AJ101+AK101 -> 2000 | AM101: =T101*AL101 -> 0 | AN101: =U101*AL101 -> 0 | AO101: =V101*AL101 -> 0 | AP101: =W101*AL101 -> 0 | AQ101: =X101*AL101 -> 0 | AR101: =Y101*AL101 -> 0 | AS101: =Z101*AL101 -> 0 | AT101: =SUM(AM101:AS101) -> 0 | AU101: =AB101*AL101 -> 6000 | AV101: =AC101*AL101 -> 0 | AW101: =AD101*AL101 -> 0 | AX101: =AE101*AL101 -> 0 | AY101: =AF101*AL101 -> 0 | AZ101: =AG101*AL101 -> 0 | BA101: =SUM(AU101:AZ101) -> 6000
A102: 86 | B102: 供应及安装Z型消声连通管600*150 | L102: =SUM(F102:K102) -> 0 | S102: =SUM(M102:R102) -> 0 | T102: 0 | U102: 0 | V102: 3 | W102: 3 | X102: 3 | Y102: 1 | Z102: 0 | AA102: =SUM(T102:Z102) -> 10 | AB102: 0 | AC102: 0 | AD102: 0 | AE102: 0 | AF102: 0 | AG102: 0 | AH102: =SUM(AB102:AG102) -> 0 | AI102: nos | AJ102: 68.75 | AK102: 337.5 | AL102: =AJ102+AK102 -> 406.25 | AM102: =T102*AL102 -> 0 | AN102: =U102*AL102 -> 0 | AO102: =V102*AL102 -> 1218.75 | AP102: =W102*AL102 -> 1218.75 | AQ102: =X102*AL102 -> 1218.75 | AR102: =Y102*AL102 -> 406.25 | AS102: =Z102*AL102 -> 0 | AT102: =SUM(AM102:AS102) -> 4062.5 | AU102: =AB102*AL102 -> 0 | AV102: =AC102*AL102 -> 0 | AW102: =AD102*AL102 -> 0 | AX102: =AE102*AL102 -> 0 | AY102: =AF102*AL102 -> 0 | AZ102: =AG102*AL102 -> 0 | BA102: =SUM(AU102:AZ102) -> 0
... A106: 90 | B106: 供应及安装消音风管 | L106: =SUM(F106:K106) -> 0 | S106: =SUM(M106:R106) -> 0 | T106: 0 | U106: 44 | V106: 0 | W106: 14 | X106: 0 | Y106: 43 | Z106: 0 | AA106: =SUM(T106:Z106) -> 101 | AB106: 0 | AC106: 0 | AD106: 0 | AE106: 0 | AF106: 0 | AG106: 0 | AH106: =SUM(AB106:AG106) -> 0 | AI106: m2 | AJ106: 100 | AK106: 337.5 | AL106: =AJ106+AK106 -> 437.5 | AM106: =T106*AL106 -> 0 | AN106: =U106*AL106 -> 19250 | AO106: =V106*AL106 -> 0 | AP106: =W106*AL106 -> 6125 | AQ106: =X106*AL106 -> 0 | AR106: =Y106*AL106 -> 18812.5 | AS106: =Z106*AL106 -> 0 | AT106: =SUM(AM106:AS106) -> 44187.5 | AU106: =AB106*AL106 -> 0 | AV106: =AC106*AL106 -> 0 | AW106: =AD106*AL106 -> 0 | AX106: =AE106*AL106 -> 0 | AY106: =AF106*AL106 -> 0 | AZ106: =AG106*AL106 -> 0 | BA106: =SUM(AU106:AZ106) -> 0
A107: 91 | B107: Air Conditioning Water System 空调水系统 | L107: =SUM(F107:K107) -> 0 | S107: =SUM(M107:R107) -> 0 | T107: 0 | U107: 0 | V107: 0 | W107: 0 | X107: 0 | Y107: 0 | Z107: 0 | AA107: =SUM(T107:Z107) -> 0 | AB107: 0 | AC107: 0 | AD107: 0 | AE107: 0 | AF107: 0 | AG107: 0 | AH107: =SUM(AB107:AG107) -> 0 | AJ107: 0 | AK107: 0 | AL107: =AJ107+AK107 -> 0 | AM107: =T107*AL107 -> 0 | AN107: =U107*AL107 -> 0 | AO107: =V107*AL107 -> 0 | AP107: =W107*AL107 -> 0 | AQ107: =X107*AL107 -> 0 | AR107: =Y107*AL107 -> 0 | AS107: =Z107*AL107 -> 0 | AT107: =SUM(AM107:AS107) -> 0 | AU107: =AB107*AL107 -> 0 | AV107: =AC107*AL107 -> 0 | AW107: =AD107*AL107 -> 0 | AX107: =AE107*AL107 -> 0 | AY107: =AF107*AL107 -> 0 | AZ107: =AG107*AL107 -> 0 | BA107: =SUM(AU107:AZ107) -> 0
A108: 92 | B108: 供应及安装Y型过滤器DN80 | D108: kitz | L108: =SUM(F108:K108) -> 0 | S108: =SUM(M108:R108) -> 0 | T108: 0 | U108: 1 | V108: 1 | W108: 1 | X108: 1 | Y108: 1 | Z108: 0 | AA108: =SUM(T108:Z108) -> 5 | AB108: 1 | AC108: 1 | AD108: 1 | AE108: 1 | AF108: 1 | AG108: 0 | AH108: =SUM(AB108:AG108) -> 5 | AI108: nos | AJ108: 100 | AK108: 975.9125 | AL108: =AJ108+AK108 -> 1075.9125 | AM108: =T108*AL108 -> 0 | AN108: =U108*AL108 -> 1075.9125 | AO108: =V108*AL108 -> 1075.9125 | AP108: =W108*AL108 -> 1075.9125 | AQ108: =X108*AL108 -> 1075.9125 | AR108: =Y108*AL108 -> 1075.9125 | AS108: =Z108*AL108 -> 0 | AT108: =SUM(AM108:AS108) -> 5379.5625 | AU108: =AB108*AL108 -> 1075.9125 | AV108: =AC108*AL108 -> 1075.9125 | AW108: =AD108*AL108 -> 1075.9125 | AX108: =AE108*AL108 -> 1075.9125 | AY108: =AF108*AL108 -> 1075.9125 | AZ108: =AG108*AL108 -> 0 | BA108: =SUM(AU108:AZ108) -> 5379.5625
A109: 93 | B109: 供应及安装Y型过滤器DN100 | D109: kitz | L109: =SUM(F109:K109) -> 0 | S109: =SUM(M109:R109) -> 0 | T109: 0 | U109: 0 | V109: 0 | W109: 0 | X109: 0 | Y109: 0 | Z109: 40 | AA109: =SUM(T109:Z109) -> 40 | AB109: 0 | AC109: 0 | AD109: 0 | AE109: 0 | AF109: 0 | AG109: 0 | AH109: =SUM(AB109:AG109) -> 0 | AI109: nos | AJ109: 125 | AK109: 1236.2375 | AL109: =AJ109+AK109 -> 1361.2375 | AM109: =T109*AL109 -> 0 | AN109: =U109*AL109 -> 0 | AO109: =V109*AL109 -> 0 | AP109: =W109*AL109 -> 0 | AQ109: =X109*AL109 -> 0 | AR109: =Y109*AL109 -> 0 | AS109: =Z109*AL109 -> 54449.5 | AT109: =SUM(AM109:AS109) -> 54449.5 | AU109: =AB109*AL109 -> 0 | AV109: =AC109*AL109 -> 0 | AW109: =AD109*AL109 -> 0 | AX109: =AE109*AL109 -> 0 | AY109: =AF109*AL109 -> 0 | AZ109: =AG109*AL109 -> 0 | BA109: =SUM(AU109:AZ109) -> 0
A110: 94 | B110: 供应及安装Y型过滤器DN125 | D110: kitz | L110: =SUM(F110:K110) -> 0 | S110: =SUM(M110:R110) -> 0 | T110: 0 | U110: 0 | V110: 0 | W110: 0 | X110: 0 | Y110: 0 | Z110: 0 | AA110: =SUM(T110:Z110) -> 0 | AB110: 0 | AC110: 0 | AD110: 0 | AE110: 0 | AF110: 0 | AG110: 7 | AH110: =SUM(AB110:AG110) -> 7 | AI110: nos | AJ110: 150 | AK110: 1881.875 | AL110: =AJ110+AK110 -> 2031.875 | AM110: =T110*AL110 -> 0 | AN110: =U110*AL110 -> 0 | AO110: =V110*AL110 -> 0 | AP110: =W110*AL110 -> 0 | AQ110: =X110*AL110 -> 0 | AR110: =Y110*AL110 -> 0 | AS110: =Z110*AL110 -> 0 | AT110: =SUM(AM110:AS110) -> 0 | AU110: =AB110*AL110 -> 0 | AV110: =AC110*AL110 -> 0 | AW110: =AD110*AL110 -> 0 | AX110: =AE110*AL110 -> 0 | AY110: =AF110*AL110 -> 0 | AZ110: =AG110*AL110 -> 14223.125 | BA110: =SUM(AU110:AZ110) -> 14223.125
A111: 95 | B111: 供应及安装Y型过滤器DN150 | D111: kitz | L111: =SUM(F111:K111) -> 0 | S111: =SUM(M111:R111) -> 0 | T111: 0 | U111: 1 | V111: 1 | W111: 1 | X111: 1 | Y111: 1 | Z111: 0 | AA111: =SUM(T111:Z111) -> 5 | AB111: 0 | AC111: 0 | AD111: 0 | AE111: 0 | AF111: 0 | AG111: 0 | AH111: =SUM(AB111:AG111) -> 0 | AI111: nos | AJ111: 162.5 | AK111: 2721.325 | AL111: =AJ111+AK111 -> 2883.825 | AM111: =T111*AL111 -> 0 | AN111: =U111*AL111 -> 2883.825 | AO111: =V111*AL111 -> 2883.825 | AP111: =W111*AL111 -> 2883.825 | AQ111: =X111*AL111 -> 2883.825 | AR111: =Y111*AL111 -> 2883.825 | AS111: =Z111*AL111 -> 0 | AT111: =SUM(AM111:AS111) -> 14419.125 | AU111: =AB111*AL111 -> 0 | AV111: =AC111*AL111 -> 0 | AW111: =AD111*AL111 -> 0 | AX111: =AE111*AL111 -> 0 | AY111: =AF111*AL111 -> 0 | AZ111: =AG111*AL111 -> 0 | BA111: =SUM(AU111:AZ111) -> 0
A112: 96 | B112: 供应及安装Y型过滤器DN200 | D112: kitz | L112: =SUM(F112:K112) -> 0 | S112: =SUM(M112:R112) -> 0 | T112: 0 | U112: 0 | V112: 0 | W112: 0 | X112: 0 | Y112: 0 | Z112: 0 | AA112: =SUM(T112:Z112) -> 0 | AB112: 0 | AC112: 0 | AD112: 0 | AE112: 0 | AF112: 0 | AG112: 1 | AH112: =SUM(AB112:AG112) -> 1 | AI112: nos | AJ112: 225 | AK112: 4662.85 | AL112: =AJ112+AK112 -> 4887.85 | AM112: =T112*AL112 -> 0 | AN112: =U112*AL112 -> 0 | AO112: =V112*AL112 -> 0 | AP112: =W112*AL112 -> 0 | AQ112: =X112*AL112 -> 0 | AR112: =Y112*AL112 -> 0 | AS112: =Z112*AL112 -> 0 | AT112: =SUM(AM112:AS112) -> 0 | AU112: =AB112*AL112 -> 0 | AV112: =AC112*AL112 -> 0 | AW112: =AD112*AL112 -> 0 | AX112: =AE112*AL112 -> 0 | AY112: =AF112*AL112 -> 0 | AZ112: =AG112*AL112 -> 4887.85 | BA112: =SUM(AU112:AZ112) -> 4887.85
A113: 97 | B113: 供应及安装Y型过滤器DN250 | D113: kitz | L113: =SUM(F113:K113) -> 0 | S113: =SUM(M113:R113) -> 0 | T113: 0 | U113: 0 | V113: 0 | W113: 0 | X113: 0 | Y113: 0 | Z113: 0 | AA113: =SUM(T113:Z113) -> 0 | AB113: 0 | AC113: 0 | AD113: 0 | AE113: 0 | AF113: 0 | AG113: 3 | AH113: =SUM(AB113:AG113) -> 3 | AI113: nos | AJ113: 325 | AK113: 7962.15 | AL113: =AJ113+AK113 -> 8287.15 | AM113: =T113*AL113 -> 0 | AN113: =U113*AL113 -> 0 | AO113: =V113*AL113 -> 0 | AP113: =W113*AL113 -> 0 | AQ113: =X113*AL113 -> 0 | AR113: =Y113*AL113 -> 0 | AS113: =Z113*AL113 -> 0 | AT113: =SUM(AM113:AS113) -> 0 | AU113: =AB113*AL113 -> 0 | AV113: =AC113*AL113 -> 0 | AW113: =AD113*AL113 -> 0 | AX113: =AE113*AL113 -> 0 | AY113: =AF113*AL113 -> 0 | AZ113: =AG113*AL113 -> 24861.45 | BA113: =SUM(AU113:AZ113) -> 24861.45
A114: 98 | B114: 安装电动调节阀（DN80-150） | D114: kitz | L114: =SUM(F114:K114) -> 0 | S114: =SUM(M114:R114) -> 0 | T114: 0 | U114: 2 | V114: 2 | W114: 2 | X114: 2 | Y114: 2 | Z114: 4 | AA114: =SUM(T114:Z114) -> 14 | AB114: 2 | AC114: 2 | AD114: 2 | AE114: 2 | AF114: 2 | AG114: 0 | AH114: =SUM(AB114:AG114) -> 10 | AI114: nos | AJ114: 750 | AK114: 0 | AL114: =AJ114+AK114 -> 750 | AM114: =T114*AL114 -> 0 | AN114: =U114*AL114 -> 1500 | AO114: =V114*AL114 -> 1500 | AP114: =W114*AL114 -> 1500 | AQ114: =X114*AL114 -> 1500 | AR114: =Y114*AL114 -> 1500 | AS114: =Z114*AL114 -> 3000 | AT114: =SUM(AM114:AS114) -> 10500 | AU114: =AB114*AL114 -> 1500 | AV114: =AC114*AL114 -> 1500 | AW114: =AD114*AL114 -> 1500 | AX114: =AE114*AL114 -> 1500 | AY114: =AF114*AL114 -> 1500 | AZ114: =AG114*AL114 -> 0 | BA114: =SUM(AU114:AZ114) -> 7500
A115: 99 | B115: 安装电动调节阀DN（200-350） | L115: =SUM(F115:K115) -> 0 | S115: =SUM(M115:R115) -> 0 | T115: 0 | U115: 0 | V115: 0 | W115: 0 | X115: 0 | Y115: 0 | Z115: 0 | AA115: =SUM(T115:Z115) -> 0 | AB115: 0 | AC115: 0 | AD115: 0 | AE115: 0 | AF115: 0 | AG115: 6 | AH115: =SUM(AB115:AG115) -> 6 | AI115: nos | AJ115: 1250 | AK115: 0 | AL115: =AJ115+AK115 -> 1250 | AM115: =T115*AL115 -> 0 | AN115: =U115*AL115 -> 0 | AO115: =V115*AL115 -> 0 | AP115: =W115*AL115 -> 0 | AQ115: =X115*AL115 -> 0 | AR115: =Y115*AL115 -> 0 | AS115: =Z115*AL115 -> 0 | AT115: =SUM(AM115:AS115) -> 0 | AU115: =AB115*AL115 -> 0 | AV115: =AC115*AL115 -> 0 | AW115: =AD115*AL115 -> 0 | AX115: =AE115*AL115 -> 0 | AY115: =AF115*AL115 -> 0 | AZ115: =AG115*AL115 -> 7500 | BA115: =SUM(AU115:AZ115) -> 7500
A116: 100 | B116: 安装电动双位蝶阀（DN125-200） | L116: =SUM(F116:K116) -> 0 | S116: =SUM(M116:R116) -> 0 | T116: 0 | U116: 0 | V116: 0 | W116: 0 | X116: 0 | Y116: 0 | Z116: 4 | AA116: =SUM(T116:Z116) -> 4 | AB116: 0 | AC116: 0 | AD116: 0 | AE116: 0 | AF116: 0 | AG116: 4 | AH116: =SUM(AB116:AG116) -> 4 | AI116: nos | AJ116: 1000 | AK116: 0 | AL116: =AJ116+AK116 -> 1000 | AM116: =T116*AL116 -> 0 | AN116: =U116*AL116 -> 0 | AO116: =V116*AL116 -> 0 | AP116: =W116*AL116 -> 0 | AQ116: =X116*AL116 -> 0 | AR116: =Y116*AL116 -> 0 | AS116: =Z116*AL116 -> 4000 | AT116: =SUM(AM116:AS116) -> 4000 | AU116: =AB116*AL116 -> 0 | AV116: =AC116*AL116 -> 0 | AW116: =AD116*AL116 -> 0 | AX116: =AE116*AL116 -> 0 | AY116: =AF116*AL116 -> 0 | AZ116: =AG116*AL116 -> 4000 | BA116: =SUM(AU116:AZ116) -> 4000
A117: 101 | B117: 供应及安装蝶阀DN100 | D117: kitz | L117: =SUM(F117:K117) -> 0 | S117: =SUM(M117:R117) -> 0 | T117: 0 | U117: 0 | V117: 0 | W117: 0 | X117: 0 | Y117: 0 | Z117: 0 | AA117: =SUM(T117:Z117) -> 0 | AB117: 0 | AC117: 0 | AD117: 0 | AE117: 0 | AF117: 0 | AG117: 10 | AH117: =SUM(AB117:AG117) -> 10 | AI117: nos | AJ117: 150 | AK117: 687.5 | AL117: =AJ117+AK117 -> 837.5 | AM117: =T117*AL117 -> 0 | AN117: =U117*AL117 -> 0 | AO117: =V117*AL117 -> 0 | AP117: =W117*AL117 -> 0 | AQ117: =X117*AL117 -> 0 | AR117: =Y117*AL117 -> 0 | AS117: =Z117*AL117 -> 0 | AT117: =SUM(AM117:AS117) -> 0 | AU117: =AB117*AL117 -> 0 | AV117: =AC117*AL117 -> 0 | AW117: =AD117*AL117 -> 0 | AX117: =AE117*AL117 -> 0 | AY117: =AF117*AL117 -> 0 | AZ117: =AG117*AL117 -> 8375 | BA117: =SUM(AU117:AZ117) -> 8375
A118: 102 | B118: 供应及安装蝶阀DN125 | D118: kitz | L118: =SUM(F118:K118) -> 0 | S118: =SUM(M118:R118) -> 0 | T118: 0 | U118: 0 | V118: 0 | W118: 0 | X118: 0 | Y118: 0 | Z118: 6 | AA118: =SUM(T118:Z118) -> 6 | AB118: 0 | AC118: 0 | AD118: 0 | AE118: 0 | AF118: 0 | AG118: 21 | AH118: =SUM(AB118:AG118) -> 21 | AI118: nos | AJ118: 150 | AK118: 809.6375 | AL118: =AJ118+AK118 -> 959.6375 | AM118: =T118*AL118 -> 0 | AN118: =U118*AL118 -> 0 | AO118: =V118*AL118 -> 0 | AP118: =W118*AL118 -> 0 | AQ118: =X118*AL118 -> 0 | AR118: =Y118*AL118 -> 0 | AS118: =Z118*AL118 -> 5757.825 | AT118: =SUM(AM118:AS118) -> 5757.825 | AU118: =AB118*AL118 -> 0 | AV118: =AC118*AL118 -> 0 | AW118: =AD118*AL118 -> 0 | AX118: =AE118*AL118 -> 0 | AY118: =AF118*AL118 -> 0 | AZ118: =AG118*AL118 -> 20152.388 | BA118: =SUM(AU118:AZ118) -> 20152.388
...

Sheet HYE-option
A2: Bill of Quantity for Build General Contractor Works
A3: =[41]Summary!A2 -> CHN, Shanghai Campus Building 1 RF Project
A4: =[41]Summary!A4 -> Issue Date: 2026/08/04
A6: Name of Tenderer:____HYE________________________________
A8: DO NOT change the form of this Schdule of Rates, any changes or ideas please use "Please specify" rows 不要自行更改或修改表格格式，任何改动需使用”请列明“行
A10: No. 序号 | B10: DESCRIPTION OF WORKS 描述 | C10: Material Code 材料编号 | D10: Spec.Brand 品牌型号 | E10: Refer. Quantity/参考数量 | T10: Tender Quantity/ 投标数量 | AI10: Unit 单位 | AJ10: Unit Rate(¥) 单价 | AM10: Total(RMB)/ 合计 | AU10: Total(RMB)/ 合计 | BB10: Remarks 备注
E11: Phase 1 短翼 | M11: Phase 2 长翼 | T11: Phase 1 短翼 | AB11: Phase 2 长翼 | AJ11: Labor | AK11: Material | AL11: Total | AM11: Phase 1 短翼 | AU11: Phase 2 长翼
E12: -1F | F12: 1F | G12: 2F | H12: 3F | I12: 4F | J12: 5F | K12: Roof | L12: Total | M12: 1F | N12: 2F | O12: 3F | P12: 4F | Q12: 5F | R12: Roof | S12: Total | T12: -1F | U12: 1F | V12: 2F | W12: 3F | X12: 4F | Y12: 5F | Z12: Roof | AA12: Total | AB12: 1F | AC12: 2F | AD12: 3F | AE12: 4F | AF12: 5F | AG12: Roof | AH12: Total | AJ12: 人工 | AK12: 材料 | AL12: 小计 | AM12: -1F | AN12: 1F | AO12: 2F | AP12: 3F | AQ12: 4F | AR12: 5F | AS12: Roof | AT12: Total | AU12: 1F | AV12: 2F | AW12: 3F | AX12: 4F | AY12: 5F | AZ12: Roof | BA12: Total
A13: 1 | B13: Air-conditioning Works 空调工程
A14: 1 | B14: Ventilation System 通风系统 | L14: =SUM(F14:K14) -> 0 | S14: =SUM(M14:R14) -> 0 | T14: 0 | Z14: 0 | AA14: =SUM(T14:Z14) -> 0 | AG14: 0 | AH14: =SUM(AB14:AG14) -> 0 | AL14: =AJ14+AK14 -> 0 | AM14: =T14*AL14 -> 0 | AN14: =U14*AL14 -> 0 | AO14: =V14*AL14 -> 0 | AP14: =W14*AL14 -> 0 | AQ14: =X14*AL14 -> 0 | AR14: =Y14*AL14 -> 0 | AS14: =Z14*AL14 -> 0 | AT14: =SUM(AM14:AS14) -> 0 | AU14: =AB14*AL14 -> 0 | AV14: =AC14*AL14 -> 0 | AW14: =AD14*AL14 -> 0 | AX14: =AE14*AL14 -> 0 | AY14: =AF14*AL14 -> 0 | AZ14: =AG14*AL14 -> 0 | BA14: =SUM(AU14:AZ14) -> 0
A15: 1.01 | B15: FCP控制箱(安装于机房) 3块Flexface电子板 3组出回风感应器 | L15: =SUM(F15:K15) -> 0 | S15: =SUM(M15:R15) -> 0 | T15: 0 | U15: 1 | V15: 1 | W15: 1 | X15: 1 | Y15: 1 | Z15: 0 | AA15: =SUM(T15:Z15) -> 5 | AB15: 1 | AC15: 1 | AD15: 1 | AE15: 1 | AF15: 1 | AG15: 0 | AH15: =SUM(AB15:AG15) -> 5 | AI15: set | AJ15: 122500 | AL15: =AJ15+AK15 -> 122500 | AM15: =T15*AL15 -> 0 | AN15: =U15*AL15 -> 122500 | AO15: =V15*AL15 -> 122500 | AP15: =W15*AL15 -> 122500 | AQ15: =X15*AL15 -> 122500 | AR15: =Y15*AL15 -> 122500 | AS15: =Z15*AL15 -> 0 | AT15: =SUM(AM15:AS15) -> 612500 | AU15: =AB15*AL15 -> 122500 | AV15: =AC15*AL15 -> 122500 | AW15: =AD15*AL15 -> 122500 | AX15: =AE15*AL15 -> 122500 | AY15: =AF15*AL15 -> 122500 | AZ15: =AG15*AL15 -> 0 | BA15: =SUM(AU15:AZ15) -> 612500
A16: 1.02 | B16: FCP控制箱(安装于机房) 2块Flexface电子板 2组出回风感应器 1个 Flexmatic Touch Controller w/ BMS | L16: =SUM(F16:K16) -> 0 | S16: =SUM(M16:R16) -> 0 | T16: 0 | U16: 1 | V16: 1 | W16: 1 | X16: 1 | Y16: 1 | Z16: 0 | AA16: =SUM(T16:Z16) -> 5 | AB16: 1 | AC16: 1 | AD16: 1 | AE16: 1 | AF16: 1 | AG16: 0 | AH16: =SUM(AB16:AG16) -> 5 | AI16: set | AJ16: 111250 | AL16: =AJ16+AK16 -> 111250 | AM16: =T16*AL16 -> 0 | AN16: =U16*AL16 -> 111250 | AO16: =V16*AL16 -> 111250 | AP16: =W16*AL16 -> 111250 | AQ16: =X16*AL16 -> 111250 | AR16: =Y16*AL16 -> 111250 | AS16: =Z16*AL16 -> 0 | AT16: =SUM(AM16:AS16) -> 556250 | AU16: =AB16*AL16 -> 111250 | AV16: =AC16*AL16 -> 111250 | AW16: =AD16*AL16 -> 111250 | AX16: =AE16*AL16 -> 111250 | AY16: =AF16*AL16 -> 111250 | AZ16: =AG16*AL16 -> 0 | BA16: =SUM(AU16:AZ16) -> 556250
L17: =SUM(F17:K17) -> 0 | S17: =SUM(M17:R17) -> 0 | T17: 0 | Z17: 0 | AA17: =SUM(T17:Z17) -> 0 | AG17: 0 | AH17: =SUM(AB17:AG17) -> 0 | AL17: =AJ17+AK17 -> 0 | AM17: =T17*AL17 -> 0 | AN17: =U17*AL17 -> 0 | AO17: =V17*AL17 -> 0 | AP17: =W17*AL17 -> 0 | AQ17: =X17*AL17 -> 0 | AR17: =Y17*AL17 -> 0 | AS17: =Z17*AL17 -> 0 | AT17: =SUM(AM17:AS17) -> 0 | AU17: =AB17*AL17 -> 0 | AV17: =AC17*AL17 -> 0 | AW17: =AD17*AL17 -> 0 | AX17: =AE17*AL17 -> 0 | AY17: =AF17*AL17 -> 0 | AZ17: =AG17*AL17 -> 0 | BA17: =SUM(AU17:AZ17) -> 0
L18: =SUM(F18:K18) -> 0 | S18: =SUM(M18:R18) -> 0 | T18: 0 | Z18: 0 | AA18: =SUM(T18:Z18) -> 0 | AG18: 0 | AH18: =SUM(AB18:AG18) -> 0 | AL18: =AJ18+AK18 -> 0 | AM18: =SUBTOTAL(9,AM13:AM16) -> 0 | AN18: =SUBTOTAL(9,AN13:AN16) -> 233750 | AO18: =SUBTOTAL(9,AO13:AO16) -> 233750 | AP18: =SUBTOTAL(9,AP13:AP16) -> 233750 | AQ18: =SUBTOTAL(9,AQ13:AQ16) -> 233750 | AR18: =SUBTOTAL(9,AR13:AR16) -> 233750 | AS18: =SUBTOTAL(9,AS13:AS16) -> 0 | AT18: =SUBTOTAL(9,AT13:AT16) -> 1168750 | ... BA18: =SUBTOTAL(9,BA13:BA16) -> 1168750
L19: =SUM(F19:K19) -> 0 | S19: =SUM(M19:R19) -> 0 | T19: 0 | Z19: 0 | AA19: =SUM(T19:Z19) -> 0 | AG19: 0 | AH19: =SUM(AB19:AG19) -> 0 | AL19: =AJ19+AK19 -> 0 | AM19: =T19*AL19 -> 0 | AN19: =U19*AL19 -> 0 | AO19: =V19*AL19 -> 0 | AP19: =W19*AL19 -> 0 | AQ19: =X19*AL19 -> 0 | AR19: =Y19*AL19 -> 0 | AS19: =Z19*AL19 -> 0 | AT19: =SUM(AM19:AS19) -> 0 | AU19: =AB19*AL19 -> 0 | AV19: =AC19*AL19 -> 0 | AW19: =AD19*AL19 -> 0 | AX19: =AE19*AL19 -> 0 | AY19: =AF19*AL19 -> 0 | AZ19: =AG19*AL19 -> 0 | BA19: =SUM(AU19:AZ19) -> 0
A20: 2 | B20: Diesel generator muffler for noise reduction-柴油发电机吸降噪百叶
A21: 2.01 | B21: Provide and install diesel generator mufflers for noise reduction 提供及安装柴油发电机吸降噪百叶 | L21: =SUM(F21:K21) -> 0 | S21: =SUM(M21:R21) -> 0 | T21: 0 | U21: 108 | Z21: 0 | AA21: =SUM(T21:Z21) -> 108 | AG21: 0 | AH21: =SUM(AB21:AG21) -> 0 | AI21: sm | AJ21: 250 | AK21: 1130 | AL21: =AJ21+AK21 -> 1380 | AM21: =T21*AL21 -> 0 | AN21: =U21*AL21 -> 149040 | AO21: =V21*AL21 -> 0 | AP21: =W21*AL21 -> 0 | AQ21: =X21*AL21 -> 0 | AR21: =Y21*AL21 -> 0 | AS21: =Z21*AL21 -> 0 | AT21: =SUM(AM21:AS21) -> 149040 | AU21: =AB21*AL21 -> 0 | AV21: =AC21*AL21 -> 0 | AW21: =AD21*AL21 -> 0 | AX21: =AE21*AL21 -> 0 | AY21: =AF21*AL21 -> 0 | AZ21: =AG21*AL21 -> 0 | BA21: =SUM(AU21:AZ21) -> 0
L22: =SUM(F22:K22) -> 0 | S22: =SUM(M22:R22) -> 0 | T22: 0 | Z22: 0 | AA22: =SUM(T22:Z22) -> 0 | AG22: 0 | AH22: =SUM(AB22:AG22) -> 0 | AL22: =AJ22+AK22 -> 0 | AM22: =T22*AL22 -> 0 | AN22: =U22*AL22 -> 0 | AO22: =V22*AL22 -> 0 | AP22: =W22*AL22 -> 0 | AQ22: =X22*AL22 -> 0 | AR22: =Y22*AL22 -> 0 | AS22: =Z22*AL22 -> 0 | AT22: =SUM(AM22:AS22) -> 0 | AU22: =AB22*AL22 -> 0 | AV22: =AC22*AL22 -> 0 | AW22: =AD22*AL22 -> 0 | AX22: =AE22*AL22 -> 0 | AY22: =AF22*AL22 -> 0 | AZ22: =AG22*AL22 -> 0 | BA22: =SUM(AU22:AZ22) -> 0
L23: =SUM(F23:K23) -> 0 | S23: =SUM(M23:R23) -> 0 | T23: 0 | Z23: 0 | AA23: =SUM(T23:Z23) -> 0 | AG23: 0 | AH23: =SUM(AB23:AG23) -> 0 | AL23: =AJ23+AK23 -> 0 | AM23: =T23*AL23 -> 0 | AN23: =U23*AL23 -> 0 | AO23: =V23*AL23 -> 0 | AP23: =W23*AL23 -> 0 | AQ23: =X23*AL23 -> 0 | AR23: =Y23*AL23 -> 0 | AS23: =Z23*AL23 -> 0 | AT23: =SUM(AM23:AS23) -> 0 | AU23: =AB23*AL23 -> 0 | AV23: =AC23*AL23 -> 0 | AW23: =AD23*AL23 -> 0 | AX23: =AE23*AL23 -> 0 | AY23: =AF23*AL23 -> 0 | AZ23: =AG23*AL23 -> 0 | BA23: =SUM(AU23:AZ23) -> 0
L24: =SUM(F24:K24) -> 0 | S24: =SUM(M24:R24) -> 0 | T24: 0 | Z24: 0 | AA24: =SUM(T24:Z24) -> 0 | AG24: 0 | AH24: =SUM(AB24:AG24) -> 0 | AL24: =AJ24+AK24 -> 0 | AM24: =SUBTOTAL(9,AM19:AM22) -> 0 | AN24: =SUBTOTAL(9,AN19:AN22) -> 149040 | AO24: =SUBTOTAL(9,AO19:AO22) -> 0 | AP24: =SUBTOTAL(9,AP19:AP22) -> 0 | AQ24: =SUBTOTAL(9,AQ19:AQ22) -> 0 | AR24: =SUBTOTAL(9,AR19:AR22) -> 0 | AS24: =SUBTOTAL(9,AS19:AS22) -> 0 | AT24: =SUBTOTAL(9,AT19:AT23) -> 149040 | AU24: =SUBTOTAL(9,AU19:AU22) -> 0 | AV24: =SUBTOTAL(9,AV19:AV22) -> 0 | AW24: =SUBTOTAL(9,AW19:AW22) -> 0 | AX24: =SUBTOTAL(9,AX19:AX22) -> 0 | AY24: =SUBTOTAL(9,AY19:AY22) -> 0 | AZ24: =SUBTOTAL(9,AZ19:AZ22) -> 0 | BA24: =SUBTOTAL(9,BA19:BA22) -> 0
L25: =SUM(F25:K25) -> 0 | S25: =SUM(M25:R25) -> 0 | T25: 0 | Z25: 0 | AA25: =SUM(T25:Z25) -> 0 | AG25: 0 | AH25: =SUM(AB25:AG25) -> 0 | AL25: =AJ25+AK25 -> 0 | AM25: =T25*AL25 -> 0 | AN25: =U25*AL25 -> 0 | AO25: =V25*AL25 -> 0 | AP25: =W25*AL25 -> 0 | AQ25: =X25*AL25 -> 0 | AR25: =Y25*AL25 -> 0 | AS25: =Z25*AL25 -> 0 | AT25: =SUM(AM25:AS25) -> 0 | AU25: =AB25*AL25 -> 0 | AV25: =AC25*AL25 -> 0 | AW25: =AD25*AL25 -> 0 | AX25: =AE25*AL25 -> 0 | AY25: =AF25*AL25 -> 0 | AZ25: =AG25*AL25 -> 0 | BA25: =SUM(AU25:AZ25) -> 0
A26: 3 | B26: System partition sealing strip系统隔断收口条 | AA26: =SUM(T26:Z26) -> 0 | AH26: =SUM(AB26:AG26) -> 0
A27: =A26+0.01 -> 3.01 | B27: Supply and install painted metal trim for system partitions 提供及安装系统隔断烤漆金属收口条 | C27: B1 | L27: =SUM(F27:K27) -> 0 | S27: =SUM(M27:R27) -> 0 | U27: 46.392 | V27: 39.12 | W27: 32.688 | X27: 25.992 | Y27: 36.024 | AA27: =SUM(T27:Z27) -> 180.216 | AB27: 52.992 | AC27: 58.752 | AD27: 59.808 | AE27: 56.64 | AF27: 26.88 | AH27: =SUM(AB27:AG27) -> 255.072 | AI27: sm | AJ27: 108 | AK27: 72 | AL27: =AJ27+AK27 -> 180 | AM27: =T27*AL27 -> 0 | AN27: =U27*AL27 -> 8350.56 | AO27: =V27*AL27 -> 7041.6 | AP27: =W27*AL27 -> 5883.84 | AQ27: =X27*AL27 -> 4678.56 | AR27: =Y27*AL27 -> 6484.32 | AS27: =Z27*AL27 -> 0 | AT27: =SUM(AM27:AS27) -> 32438.88 | AU27: =AB27*AL27 -> 9538.56 | AV27: =AC27*AL27 -> 10575.36 | AW27: =AD27*AL27 -> 10765.44 | AX27: =AE27*AL27 -> 10195.2 | AY27: =AF27*AL27 -> 4838.4 | AZ27: =AG27*AL27 -> 0 | BA27: =SUM(AU27:AZ27) -> 45912.96 | BD27: =1217*180 -> 219060
A28: =A27+0.01 -> 3.02 | B28: Supply and install painted metal trim for fire-rated system partitions 提供及安装防火系统隔断烤漆金属收口条 | C28: B2 | L28: =SUM(F28:K28) -> 0 | S28: =SUM(M28:R28) -> 0 | U28: 32.424 | V28: 28.128 | W28: 36.48 | X28: 26.16 | Y28: 47.208 | AA28: =SUM(T28:Z28) -> 170.4 | AB28: 34.32 | AC28: 47.112 | AD28: 68.496 | AE28: 61.8 | AF28: 50.448 | AH28: =SUM(AB28:AG28) -> 262.176 | AI28: sm | AJ28: 108 | AK28: 72 | AL28: =AJ28+AK28 -> 180 | AM28: =T28*AL28 -> 0 | AN28: =U28*AL28 -> 5836.32 | AO28: =V28*AL28 -> 5063.04 | AP28: =W28*AL28 -> 6566.4 | AQ28: =X28*AL28 -> 4708.8 | AR28: =Y28*AL28 -> 8497.44 | AS28: =Z28*AL28 -> 0 | AT28: =SUM(AM28:AS28) -> 30672 | AU28: =AB28*AL28 -> 6177.6 | AV28: =AC28*AL28 -> 8480.16 | AW28: =AD28*AL28 -> 12329.28 | AX28: =AE28*AL28 -> 11124 | AY28: =AF28*AL28 -> 9080.64 | AZ28: =AG28*AL28 -> 0 | BA28: =SUM(AU28:AZ28) -> 47191.68
A29: =A28+0.01 -> 3.03 | B29: Supply and install painted metal trim for system glass doors 提供及安装系统玻璃门烤漆金属收口条 | C29: D1a | L29: =SUM(F29:K29) -> 0 | S29: =SUM(M29:R29) -> 0 | U29: 23 | V29: 25 | W29: 29 | X29: 25 | Y29: 33 | AA29: =SUM(T29:Z29) -> 135 | AB29: 36 | AC29: 43 | AD29: 46 | AE29: 46 | AF29: 32 | AH29: =SUM(AB29:AG29) -> 203 | AI29: sm | AJ29: 108 | AK29: 72 | AL29: =AJ29+AK29 -> 180 | AM29: =T29*AL29 -> 0 | AN29: =U29*AL29 -> 4140 | AO29: =V29*AL29 -> 4500 | AP29: =W29*AL29 -> 5220 | AQ29: =X29*AL29 -> 4500 | AR29: =Y29*AL29 -> 5940 | AS29: =Z29*AL29 -> 0 | AT29: =SUM(AM29:AS29) -> 24300 | AU29: =AB29*AL29 -> 6480 | AV29: =AC29*AL29 -> 7740 | AW29: =AD29*AL29 -> 8280 | AX29: =AE29*AL29 -> 8280 | AY29: =AF29*AL29 -> 5760 | AZ29: =AG29*AL29 -> 0 | BA29: =SUM(AU29:AZ29) -> 36540
A30: =A29+0.01 -> 3.04 | B30: Supply and install painted metal trim for system glass doors 提供及安装系统玻璃门烤漆金属收口条 | C30: D1b | L30: =SUM(F30:K30) -> 0 | S30: =SUM(M30:R30) -> 0 | U30: 3 | V30: 2 | W30: 2 | X30: 2 | Y30: 2 | AA30: =SUM(T30:Z30) -> 11 | AH30: =SUM(AB30:AG30) -> 0 | AI30: sm | AJ30: 108 | AK30: 72 | AL30: =AJ30+AK30 -> 180 | AM30: =T30*AL30 -> 0 | AN30: =U30*AL30 -> 540 | AO30: =V30*AL30 -> 360 | AP30: =W30*AL30 -> 360 | AQ30: =X30*AL30 -> 360 | AR30: =Y30*AL30 -> 360 | AS30: =Z30*AL30 -> 0 | AT30: =SUM(AM30:AS30) -> 1980 | AU30: =AB30*AL30 -> 0 | AV30: =AC30*AL30 -> 0 | AW30: =AD30*AL30 -> 0 | AX30: =AE30*AL30 -> 0 | AY30: =AF30*AL30 -> 0 | AZ30: =AG30*AL30 -> 0 | BA30: =SUM(AU30:AZ30) -> 0
L31: =SUM(F31:K31) -> 0 | S31: =SUM(M31:R31) -> 0 | T31: 0 | Z31: 0 | AA31: =SUM(T31:Z31) -> 0 | AG31: 0 | AH31: =SUM(AB31:AG31) -> 0 | AL31: =AJ31+AK31 -> 0 | AM31: =T31*AL31 -> 0 | AN31: =U31*AL31 -> 0 | AO31: =V31*AL31 -> 0 | AP31: =W31*AL31 -> 0 | AQ31: =X31*AL31 -> 0 | AR31: =Y31*AL31 -> 0 | AS31: =Z31*AL31 -> 0 | AT31: =SUM(AM31:AS31) -> 0 | AU31: =AB31*AL31 -> 0 | AV31: =AC31*AL31 -> 0 | AW31: =AD31*AL31 -> 0 | AX31: =AE31*AL31 -> 0 | AY31: =AF31*AL31 -> 0 | AZ31: =AG31*AL31 -> 0 | BA31: =SUM(AU31:AZ31) -> 0
L32: =SUM(F32:K32) -> 0 | S32: =SUM(M32:R32) -> 0 | T32: 0 | Z32: 0 | AA32: =SUM(T32:Z32) -> 0 | AG32: 0 | AH32: =SUM(AB32:AG32) -> 0 | AL32: =AJ32+AK32 -> 0 | AM32: =T32*AL32 -> 0 | AN32: =U32*AL32 -> 0 | AO32: =V32*AL32 -> 0 | AP32: =W32*AL32 -> 0 | AQ32: =X32*AL32 -> 0 | AR32: =Y32*AL32 -> 0 | AS32: =Z32*AL32 -> 0 | AT32: =SUM(AM32:AS32) -> 0 | AU32: =AB32*AL32 -> 0 | AV32: =AC32*AL32 -> 0 | AW32: =AD32*AL32 -> 0 | AX32: =AE32*AL32 -> 0 | AY32: =AF32*AL32 -> 0 | AZ32: =AG32*AL32 -> 0 | BA32: =SUM(AU32:AZ32) -> 0
L33: =SUM(F33:K33) -> 0 | S33: =SUM(M33:R33) -> 0 | T33: 0 | Z33: 0 | AA33: =SUM(T33:Z33) -> 0 | AG33: 0 | AH33: =SUM(AB33:AG33) -> 0 | AL33: =AJ33+AK33 -> 0 | AM33: =SUBTOTAL(9,AM25:AM31) -> 0 | AN33: =SUBTOTAL(9,AN25:AN31) -> 18866.88 | AO33: =SUBTOTAL(9,AO25:AO31) -> 16964.64 | AP33: =SUBTOTAL(9,AP25:AP31) -> 18030.24 | AQ33: =SUBTOTAL(9,AQ25:AQ31) -> 14247.36 | AR33: =SUBTOTAL(9,AR25:AR31) -> 21281.76 | AS33: =SUBTOTAL(9,AS25:AS31) -> 0 | AT33: =SUBTOTAL(9,AT27:AT32) -> 89390.88 | AU33: =SUBTOTAL(9,AU25:AU31) -> 22196.16 | AV33: =SUBTOTAL(9,AV25:AV31) -> 26795.52 | AW33: =SUBTOTAL(9,AW25:AW31) -> 31374.72 | AX33: =SUBTOTAL(9,AX25:AX31) -> 29599.2 | AY33: =SUBTOTAL(9,AY25:AY31) -> 19679.04 | AZ33: =SUBTOTAL(9,AZ25:AZ31) -> 0 | BA33: =SUBTOTAL(9,BA25:BA31) -> 129644.64
L34: =SUM(F34:K34) -> 0 | S34: =SUM(M34:R34) -> 0 | T34: 0 | Z34: 0 | AA34: =SUM(T34:Z34) -> 0 | AG34: 0 | AH34: =SUM(AB34:AG34) -> 0 | AL34: =AJ34+AK34 -> 0 | AM34: =T34*AL34 -> 0 | AN34: =U34*AL34 -> 0 | AO34: =V34*AL34 -> 0 | AP34: =W34*AL34 -> 0 | AQ34: =X34*AL34 -> 0 | AR34: =Y34*AL34 -> 0 | AS34: =Z34*AL34 -> 0 | AT34: =SUM(AM34:AS34) -> 0 | AU34: =AB34*AL34 -> 0 | AV34: =AC34*AL34 -> 0 | AW34: =AD34*AL34 -> 0 | AX34: =AE34*AL34 -> 0 | AY34: =AF34*AL34 -> 0 | AZ34: =AG34*AL34 -> 0 | BA34: =SUM(AU34:AZ34) -> 0
L35: =SUM(F35:K35) -> 0 | S35: =SUM(M35:R35) -> 0 | T35: 0 | Z35: 0 | AA35: =SUM(T35:Z35) -> 0 | AG35: 0 | AH35: =SUM(AB35:AG35) -> 0 | AL35: =AJ35+AK35 -> 0 | AM35: =T35*AL35 -> 0 | AN35: =U35*AL35 -> 0 | AO35: =V35*AL35 -> 0 | AP35: =W35*AL35 -> 0 | AQ35: =X35*AL35 -> 0 | AR35: =Y35*AL35 -> 0 | AS35: =Z35*AL35 -> 0 | AT35: =SUM(AM35:AS35) -> 0 | AU35: =AB35*AL35 -> 0 | AV35: =AC35*AL35 -> 0 | AW35: =AD35*AL35 -> 0 | AX35: =AE35*AL35 -> 0 | AY35: =AF35*AL35 -> 0 | AZ35: =AG35*AL35 -> 0 | BA35: =SUM(AU35:AZ35) -> 0
